Workbook
Name CareCosts: Constants!$W$4:$X$10
Name CCBHourlyRate: Constants!$R$4
Name CCBMaxHours: Constants!$R$3
Name CCBThreshold: Constants!$R$5
Name CCBThresholdModifier: Constants!$R$6
Name CCRMax: Constants!$R$8
Name CCRRate: Constants!$R$7
Name EmployeeSuper: Constants!$K$4:$L$7
Name EmployerSuper: Constants!$H$4:$I$13
Name FixedTax: Constants!$A$4:$B$8
Name HELP: Constants!$E$4:$F$12
Name Holidays: Constants!$U$3:$U$14
Name IncomeThreshold: Constants!$A$4:$A$8
Name Rooms: Constants!$N$4:$O$7
Name SaturdayPenalty: Constants!$X$11
Name TaxPercentage: Constants!$A$4:$C$8

Sheet Student Details
A1: BISM7202 Assignment - Semester 1, 2018
A2: Sunshine Childcare
A3: Assignment Template
A5: Documentation
A7: Student Information | F7: Note: Student numbers are eight digits and do not begin with an 's'.
A8: Student ID | C8: Family Name | D8: Given Name
A9: 45238952 | C9: Kyaw | D9: Pyae Phyo
A11: Assumptions
A13: Replace all pre-defined name ranges that were linking to another workbook with new name ranges. Child birthday is calculated in pre-birthday cost. Advance filtering criteria apply to both the database and the database function table (total,min,avg,max). Average Weekdays from 2019 Planner is constant for throughout the year. (No reduction for holidays)
A27: Tip: To switch to the next line in one cell, use the key combination 'Alt+Enter'.

Sheet Constants
A2: Tax Table | E2: HELP Repayment Table | H2: Employer Superannuation Contribution | K2: Employee Superannuation Contribution | N2: Child Care Rooms | Q2: Family Child Care Info | T2: Holidays | W2: Child Care Costs
A3: Income | B3: Fixed Tax | C3: Tax Percentage | E3: Repayable Income | F3: Repayment Rate | H3: Position | I3: Percentage | K3: Age | L3: Percentage | N3: Age | O3: Rooms | Q3: CCB Max Hours | R3: 50 | T3: New Year's Day | U3: 43101 | W3: Age | X3: Day Rate
A4: 0 | B4: 0 | C4: 0 | E4: 55874 | F4: 0.04 | H4: Director | I4: 0.125 | K4: 25 | L4: 0.025 | N4: 0 | O4: Platypus Room | Q4: CCB Hourly Rate | R4: 0.719 | T4: Australia Day | U4: 43126 | W4: 0 | X4: 120
A5: 18200 | B5: 0 | C5: 0.19 | E5: 62239 | F5: 0.045 | H5: Deputy Director | I5: 0.12 | K5: 35 | L5: 0.03 | N5: 2 | O5: Emu Room | Q5: CCB Threshold | R5: 45114 | T5: Good Friday | U5: 43189 | W5: 1 | X5: 110
A6: 37000 | B6: 3572 | C6: 0.325 | E6: 68603 | F6: 0.05 | H6: Senior Accountant | I6: 0.115 | K6: 45 | L6: 0.035 | N6: 3 | O6: Koala Room | Q6: CCB Threshold Modifier | R6: 6.5e-06 | T6: Easter Saturday | U6: 43190 | W6: 2 | X6: 105
A7: 87000 | B7: 19822 | C7: 0.37 | E7: 72208 | F7: 0.055 | H7: Accountant | I7: 0.11 | K7: 50 | L7: 0.05 | N7: 4 | O7: Kangaroo Room | Q7: CCR Rate | R7: 0.5 | T7: Easter Sunday | U7: 43191 | W7: 3 | X7: 90
A8: 180000 | B8: 54232 | C8: 0.45 | E8: 77619 | F8: 0.06 | H8: Chef | I8: 0.1 | Q8: CCR Max | R8: 7613 | T8: Easter Monday | U8: 43192 | W8: 4 | X8: 85
E9: 84063 | F9: 0.065 | H9: Assistant Chef | I9: 0.095 | T9: Anzac Day | U9: 43215 | W9: 5 | X9: 80
E10: 88487 | F10: 0.07 | H10: Child Care Leader | I10: 0.1 | T10: Labour Day | U10: 43227 | W10: 6 | X10: Not Allowed
E11: 97378 | F11: 0.075 | H11: Child Care Worker | I11: 0.095 | T11: Ekka Wednesday | U11: 43327 | W11: Saturday Penalty | X11: 10
E12: 103766 | F12: 0.08 | H12: Junior Child Care Worker | I12: 0.095 | T12: Queen's Birthday | U12: 43374
H13: Custodial Engineer | I13: 0.095 | T13: Christmas Day | U13: 43459
T14: Boxing Day | U14: 43460

Sheet Employees & Volunteers
A1: Sunshine Employees & Volunteers
A2: First Name | B2: Last Name | C2: Gender | D2: Position | E2: HELP Debt | F2: DOB | G2: Annual Income | H2: Employer Superannuation | I2: Employee Superannuation | J2: Annual Tax | K2: HELP Withheld | L2: Net Salary
A3: Jorja | B3: Arnott | C3: Female | D3: Volunteer Carer | F3: 23303 | G3: 0 | H3: =G3* IF(D3<>"Volunteer Carer", VLOOKUP(D3,EmployerSuper,2,FALSE),0) -> 0 | I3: =IF(AND(D3<>"Volunteer Carer",YEARFRAC(DATE(2017,12,31),F3)>=25), VLOOKUP(YEARFRAC(DATE(2017,12,31),F3),EmployeeSuper,2,TRUE)*(G3-J3),0) -> 0 | J3: =VLOOKUP(G3,FixedTax,2,TRUE) +((G3-VLOOKUP(G3,IncomeThreshold,1,TRUE)) * VLOOKUP(G3,TaxPercentage,3,TRUE)) -> 0 | K3: =IF(AND(G3>55874,E3=TRUE), VLOOKUP(G3,HELP,2,TRUE), 0) *G3 -> 0 | L3: =(G3+H3)-(I3+J3) -> 0
A4: Xavier | B4: Benstead | C4: Male | D4: Custodial Engineer | F4: 23422 | G4: 35423 | H4: =G4* IF(D4<>"Volunteer Carer", VLOOKUP(D4,EmployerSuper,2,FALSE),0) -> 3365.185 | I4: =IF(AND(D4<>"Volunteer Carer",YEARFRAC(DATE(2017,12,31),F4)>=25), VLOOKUP(YEARFRAC(DATE(2017,12,31),F4),EmployeeSuper,2,TRUE)*(G4-J4),0) -> 1607.5315 | J4: =VLOOKUP(G4,FixedTax,2,TRUE) +((G4-VLOOKUP(G4,IncomeThreshold,1,TRUE)) * VLOOKUP(G4,TaxPercentage,3,TRUE)) -> 3272.37 | K4: =IF(AND(G4>55874,E4=TRUE), VLOOKUP(G4,HELP,2,TRUE), 0) *G4 -> 0 | L4: =(G4+H4)-(I4+J4) -> 33908.283
A5: Abby | B5: Dennis | C5: Female | D5: Volunteer Carer | F5: 26560 | G5: 0 | H5: =G5* IF(D5<>"Volunteer Carer", VLOOKUP(D5,EmployerSuper,2,FALSE),0) -> 0 | I5: =IF(AND(D5<>"Volunteer Carer",YEARFRAC(DATE(2017,12,31),F5)>=25), VLOOKUP(YEARFRAC(DATE(2017,12,31),F5),EmployeeSuper,2,TRUE)*(G5-J5),0) -> 0 | J5: =VLOOKUP(G5,FixedTax,2,TRUE) +((G5-VLOOKUP(G5,IncomeThreshold,1,TRUE)) * VLOOKUP(G5,TaxPercentage,3,TRUE)) -> 0 | K5: =IF(AND(G5>55874,E5=TRUE), VLOOKUP(G5,HELP,2,TRUE), 0) *G5 -> 0 | L5: =(G5+H5)-(I5+J5) -> 0
A6: Isaac | B6: Foelsche | C6: Male | D6: Custodial Engineer | F6: 27695 | G6: 35423 | H6: =G6* IF(D6<>"Volunteer Carer", VLOOKUP(D6,EmployerSuper,2,FALSE),0) -> 3365.185 | I6: =IF(AND(D6<>"Volunteer Carer",YEARFRAC(DATE(2017,12,31),F6)>=25), VLOOKUP(YEARFRAC(DATE(2017,12,31),F6),EmployeeSuper,2,TRUE)*(G6-J6),0) -> 964.5189 | J6: =VLOOKUP(G6,FixedTax,2,TRUE) +((G6-VLOOKUP(G6,IncomeThreshold,1,TRUE)) * VLOOKUP(G6,TaxPercentage,3,TRUE)) -> 3272.37 | K6: =IF(AND(G6>55874,E6=TRUE), VLOOKUP(G6,HELP,2,TRUE), 0) *G6 -> 0 | L6: =(G6+H6)-(I6+J6) -> 34551.296
A7: Claudia | B7: Philp | C7: Female | D7: Director | E7: TRUE | F7: 28843 | G7: 89534 | H7: =G7* IF(D7<>"Volunteer Carer", VLOOKUP(D7,EmployerSuper,2,FALSE),0) -> 11191.75 | I7: =IF(AND(D7<>"Volunteer Carer",YEARFRAC(DATE(2017,12,31),F7)>=25), VLOOKUP(YEARFRAC(DATE(2017,12,31),F7),EmployeeSuper,2,TRUE)*(G7-J7),0) -> 2063.2326 | J7: =VLOOKUP(G7,FixedTax,2,TRUE) +((G7-VLOOKUP(G7,IncomeThreshold,1,TRUE)) * VLOOKUP(G7,TaxPercentage,3,TRUE)) -> 20759.58 | K7: =IF(AND(G7>55874,E7=TRUE), VLOOKUP(G7,HELP,2,TRUE), 0) *G7 -> 6267.38 | L7: =(G7+H7)-(I7+J7) -> 77902.937
A8: Ellie | B8: Watson | C8: Female | D8: Child Care Leader | F8: 29039 | G8: 48310 | H8: =G8* IF(D8<>"Volunteer Carer", VLOOKUP(D8,EmployerSuper,2,FALSE),0) -> 4831 | I8: =IF(AND(D8<>"Volunteer Carer",YEARFRAC(DATE(2017,12,31),F8)>=25), VLOOKUP(YEARFRAC(DATE(2017,12,31),F8),EmployeeSuper,2,TRUE)*(G8-J8),0) -> 1231.8675 | J8: =VLOOKUP(G8,FixedTax,2,TRUE) +((G8-VLOOKUP(G8,IncomeThreshold,1,TRUE)) * VLOOKUP(G8,TaxPercentage,3,TRUE)) -> 7247.75 | K8: =IF(AND(G8>55874,E8=TRUE), VLOOKUP(G8,HELP,2,TRUE), 0) *G8 -> 0 | L8: =(G8+H8)-(I8+J8) -> 44661.382
A9: Christian | B9: Tancred | C9: Male | D9: Child Care Leader | E9: TRUE | F9: 29612 | G9: 56989 | H9: =G9* IF(D9<>"Volunteer Carer", VLOOKUP(D9,EmployerSuper,2,FALSE),0) -> 5698.9 | I9: =IF(AND(D9<>"Volunteer Carer",YEARFRAC(DATE(2017,12,31),F9)>=25), VLOOKUP(YEARFRAC(DATE(2017,12,31),F9),EmployeeSuper,2,TRUE)*(G9-J9),0) -> 1407.6172 | J9: =VLOOKUP(G9,FixedTax,2,TRUE) +((G9-VLOOKUP(G9,IncomeThreshold,1,TRUE)) * VLOOKUP(G9,TaxPercentage,3,TRUE)) -> 10068.425 | K9: =IF(AND(G9>55874,E9=TRUE), VLOOKUP(G9,HELP,2,TRUE), 0) *G9 -> 2279.56 | L9: =(G9+H9)-(I9+J9) -> 51211.858
A10: Madeline | B10: Strachan | C10: Female | D10: Child Care Leader | F10: 30078 | G10: 52487 | H10: =G10* IF(D10<>"Volunteer Carer", VLOOKUP(D10,EmployerSuper,2,FALSE),0) -> 5248.7 | I10: =IF(AND(D10<>"Volunteer Carer",YEARFRAC(DATE(2017,12,31),F10)>=25), VLOOKUP(YEARFRAC(DATE(2017,12,31),F10),EmployeeSuper,2,TRUE)*(G10-J10),0) -> 1316.4517 | J10: =VLOOKUP(G10,FixedTax,2,TRUE) +((G10-VLOOKUP(G10,IncomeThreshold,1,TRUE)) * VLOOKUP(G10,TaxPercentage,3,TRUE)) -> 8605.275 | K10: =IF(AND(G10>55874,E10=TRUE), VLOOKUP(G10,HELP,2,TRUE), 0) *G10 -> 0 | L10: =(G10+H10)-(I10+J10) -> 47813.973
A11: Taylah | B11: McMahon | C11: Female | D11: Child Care Leader | E11: TRUE | F11: 30386 | G11: 48310 | H11: =G11* IF(D11<>"Volunteer Carer", VLOOKUP(D11,EmployerSuper,2,FALSE),0) -> 4831 | I11: =IF(AND(D11<>"Volunteer Carer",YEARFRAC(DATE(2017,12,31),F11)>=25), VLOOKUP(YEARFRAC(DATE(2017,12,31),F11),EmployeeSuper,2,TRUE)*(G11-J11),0) -> 1026.5563 | J11: =VLOOKUP(G11,FixedTax,2,TRUE) +((G11-VLOOKUP(G11,IncomeThreshold,1,TRUE)) * VLOOKUP(G11,TaxPercentage,3,TRUE)) -> 7247.75 | K11: =IF(AND(G11>55874,E11=TRUE), VLOOKUP(G11,HELP,2,TRUE), 0) *G11 -> 0 | L11: =(G11+H11)-(I11+J11) -> 44866.694
A12: Sofia | B12: Goold-Adams | C12: Female | D12: Deputy Director | E12: TRUE | F12: 30545 | G12: 74879 | H12: =G12* IF(D12<>"Volunteer Carer", VLOOKUP(D12,EmployerSuper,2,FALSE),0) -> 8985.48 | I12: =IF(AND(D12<>"Volunteer Carer",YEARFRAC(DATE(2017,12,31),F12)>=25), VLOOKUP(YEARFRAC(DATE(2017,12,31),F12),EmployeeSuper,2,TRUE)*(G12-J12),0) -> 1474.9081 | J12: =VLOOKUP(G12,FixedTax,2,TRUE) +((G12-VLOOKUP(G12,IncomeThreshold,1,TRUE)) * VLOOKUP(G12,TaxPercentage,3,TRUE)) -> 15882.675 | K12: =IF(AND(G12>55874,E12=TRUE), VLOOKUP(G12,HELP,2,TRUE), 0) *G12 -> 4118.345 | L12: =(G12+H12)-(I12+J12) -> 66506.897
A13: Scarlett | B13: Seager | C13: Female | D13: Child Care Worker | F13: 31294 | G13: 40750 | H13: =G13* IF(D13<>"Volunteer Carer", VLOOKUP(D13,EmployerSuper,2,FALSE),0) -> 3871.25 | I13: =IF(AND(D13<>"Volunteer Carer",YEARFRAC(DATE(2017,12,31),F13)>=25), VLOOKUP(YEARFRAC(DATE(2017,12,31),F13),EmployeeSuper,2,TRUE)*(G13-J13),0) -> 898.98125 | J13: =VLOOKUP(G13,FixedTax,2,TRUE) +((G13-VLOOKUP(G13,IncomeThreshold,1,TRUE)) * VLOOKUP(G13,TaxPercentage,3,TRUE)) -> 4790.75 | K13: =IF(AND(G13>55874,E13=TRUE), VLOOKUP(G13,HELP,2,TRUE), 0) *G13 -> 0 | L13: =(G13+H13)-(I13+J13) -> 38931.519
A14: Sam | B14: Roth | C14: Female | D14: Volunteer Carer | E14: TRUE | F14: 32296 | G14: 0 | H14: =G14* IF(D14<>"Volunteer Carer", VLOOKUP(D14,EmployerSuper,2,FALSE),0) -> 0 | I14: =IF(AND(D14<>"Volunteer Carer",YEARFRAC(DATE(2017,12,31),F14)>=25), VLOOKUP(YEARFRAC(DATE(2017,12,31),F14),EmployeeSuper,2,TRUE)*(G14-J14),0) -> 0 | J14: =VLOOKUP(G14,FixedTax,2,TRUE) +((G14-VLOOKUP(G14,IncomeThreshold,1,TRUE)) * VLOOKUP(G14,TaxPercentage,3,TRUE)) -> 0 | K14: =IF(AND(G14>55874,E14=TRUE), VLOOKUP(G14,HELP,2,TRUE), 0) *G14 -> 0 | L14: =(G14+H14)-(I14+J14) -> 0
A15: Rachel | B15: Mansergh | C15: Female | D15: Senior Accountant | E15: TRUE | F15: 32405 | G15: 68423 | H15: =G15* IF(D15<>"Volunteer Carer", VLOOKUP(D15,EmployerSuper,2,FALSE),0) -> 7868.645 | I15: =IF(AND(D15<>"Volunteer Carer",YEARFRAC(DATE(2017,12,31),F15)>=25), VLOOKUP(YEARFRAC(DATE(2017,12,31),F15),EmployeeSuper,2,TRUE)*(G15-J15),0) -> 1365.9631 | J15: =VLOOKUP(G15,FixedTax,2,TRUE) +((G15-VLOOKUP(G15,IncomeThreshold,1,TRUE)) * VLOOKUP(G15,TaxPercentage,3,TRUE)) -> 13784.475 | K15: =IF(AND(G15>55874,E15=TRUE), VLOOKUP(G15,HELP,2,TRUE), 0) *G15 -> 3079.035 | L15: =(G15+H15)-(I15+J15) -> 61141.207
A16: Nate | B16: Marian | C16: Male | D16: Child Care Worker | F16: 32481 | G16: 40750 | H16: =G16* IF(D16<>"Volunteer Carer", VLOOKUP(D16,EmployerSuper,2,FALSE),0) -> 3871.25 | I16: =IF(AND(D16<>"Volunteer Carer",YEARFRAC(DATE(2017,12,31),F16)>=25), VLOOKUP(YEARFRAC(DATE(2017,12,31),F16),EmployeeSuper,2,TRUE)*(G16-J16),0) -> 898.98125 | J16: =VLOOKUP(G16,FixedTax,2,TRUE) +((G16-VLOOKUP(G16,IncomeThreshold,1,TRUE)) * VLOOKUP(G16,TaxPercentage,3,TRUE)) -> 4790.75 | K16: =IF(AND(G16>55874,E16=TRUE), VLOOKUP(G16,HELP,2,TRUE), 0) *G16 -> 0 | L16: =(G16+H16)-(I16+J16) -> 38931.519
A17: Alex | B17: Dakin | C17: Female | D17: Child Care Leader | E17: TRUE | F17: 32561 | G17: 56989 | H17: =G17* IF(D17<>"Volunteer Carer", VLOOKUP(D17,EmployerSuper,2,FALSE),0) -> 5698.9 | I17: =IF(AND(D17<>"Volunteer Carer",YEARFRAC(DATE(2017,12,31),F17)>=25), VLOOKUP(YEARFRAC(DATE(2017,12,31),F17),EmployeeSuper,2,TRUE)*(G17-J17),0) -> 1173.0144 | J17: =VLOOKUP(G17,FixedTax,2,TRUE) +((G17-VLOOKUP(G17,IncomeThreshold,1,TRUE)) * VLOOKUP(G17,TaxPercentage,3,TRUE)) -> 10068.425 | K17: =IF(AND(G17>55874,E17=TRUE), VLOOKUP(G17,HELP,2,TRUE), 0) *G17 -> 2279.56 | L17: =(G17+H17)-(I17+J17) -> 51446.461
A18: Isaac | B18: Dumaresq | C18: Male | D18: Chef | E18: TRUE | F18: 33064 | G18: 54326 | H18: =G18* IF(D18<>"Volunteer Carer", VLOOKUP(D18,EmployerSuper,2,FALSE),0) -> 5432.6 | I18: =IF(AND(D18<>"Volunteer Carer",YEARFRAC(DATE(2017,12,31),F18)>=25), VLOOKUP(YEARFRAC(DATE(2017,12,31),F18),EmployeeSuper,2,TRUE)*(G18-J18),0) -> 1128.0763 | J18: =VLOOKUP(G18,FixedTax,2,TRUE) +((G18-VLOOKUP(G18,IncomeThreshold,1,TRUE)) * VLOOKUP(G18,TaxPercentage,3,TRUE)) -> 9202.95 | K18: =IF(AND(G18>55874,E18=TRUE), VLOOKUP(G18,HELP,2,TRUE), 0) *G18 -> 0 | L18: =(G18+H18)-(I18+J18) -> 49427.574
A19: Indiana | B19: Gask | C19: Female | D19: Chef | E19: TRUE | F19: 33423 | G19: 54326 | H19: =G19* IF(D19<>"Volunteer Carer", VLOOKUP(D19,EmployerSuper,2,FALSE),0) -> 5432.6 | I19: =IF(AND(D19<>"Volunteer Carer",YEARFRAC(DATE(2017,12,31),F19)>=25), VLOOKUP(YEARFRAC(DATE(2017,12,31),F19),EmployeeSuper,2,TRUE)*(G19-J19),0) -> 1128.0763 | J19: =VLOOKUP(G19,FixedTax,2,TRUE) +((G19-VLOOKUP(G19,IncomeThreshold,1,TRUE)) * VLOOKUP(G19,TaxPercentage,3,TRUE)) -> 9202.95 | K19: =IF(AND(G19>55874,E19=TRUE), VLOOKUP(G19,HELP,2,TRUE), 0) *G19 -> 0 | L19: =(G19+H19)-(I19+J19) -> 49427.574
A20: Ryan | B20: Loch | C20: Male | D20: Child Care Worker | E20: TRUE | F20: 33847 | G20: 40750 | H20: =G20* IF(D20<>"Volunteer Carer", VLOOKUP(D20,EmployerSuper,2,FALSE),0) -> 3871.25 | I20: =IF(AND(D20<>"Volunteer Carer",YEARFRAC(DATE(2017,12,31),F20)>=25), VLOOKUP(YEARFRAC(DATE(2017,12,31),F20),EmployeeSuper,2,TRUE)*(G20-J20),0) -> 898.98125 | J20: =VLOOKUP(G20,FixedTax,2,TRUE) +((G20-VLOOKUP(G20,IncomeThreshold,1,TRUE)) * VLOOKUP(G20,TaxPercentage,3,TRUE)) -> 4790.75 | K20: =IF(AND(G20>55874,E20=TRUE), VLOOKUP(G20,HELP,2,TRUE), 0) *G20 -> 0 | L20: =(G20+H20)-(I20+J20) -> 38931.519
A21: Alice | B21: Crawley | C21: Female | D21: Assistant Chef | E21: TRUE | F21: 33906 | G21: 43448 | H21: =G21* IF(D21<>"Volunteer Carer", VLOOKUP(D21,EmployerSuper,2,FALSE),0) -> 4127.56 | I21: =IF(AND(D21<>"Volunteer Carer",YEARFRAC(DATE(2017,12,31),F21)>=25), VLOOKUP(YEARFRAC(DATE(2017,12,31),F21),EmployeeSuper,2,TRUE)*(G21-J21),0) -> 944.51 | J21: =VLOOKUP(G21,FixedTax,2,TRUE) +((G21-VLOOKUP(G21,IncomeThreshold,1,TRUE)) * VLOOKUP(G21,TaxPercentage,3,TRUE)) -> 5667.6 | K21: =IF(AND(G21>55874,E21=TRUE), VLOOKUP(G21,HELP,2,TRUE), 0) *G21 -> 0 | L21: =(G21+H21)-(I21+J21) -> 40963.45
A22: Mitchell | B22: Grimley | C22: Male | D22: Assistant Chef | E22: TRUE | F22: 34021 | G22: 43448 | H22: =G22* IF(D22<>"Volunteer Carer", VLOOKUP(D22,EmployerSuper,2,FALSE),0) -> 4127.56 | I22: =IF(AND(D22<>"Volunteer Carer",YEARFRAC(DATE(2017,12,31),F22)>=25), VLOOKUP(YEARFRAC(DATE(2017,12,31),F22),EmployeeSuper,2,TRUE)*(G22-J22),0) -> 0 | J22: =VLOOKUP(G22,FixedTax,2,TRUE) +((G22-VLOOKUP(G22,IncomeThreshold,1,TRUE)) * VLOOKUP(G22,TaxPercentage,3,TRUE)) -> 5667.6 | K22: =IF(AND(G22>55874,E22=TRUE), VLOOKUP(G22,HELP,2,TRUE), 0) *G22 -> 0 | L22: =(G22+H22)-(I22+J22) -> 41907.96
A23: Maddison | B23: Stump | C23: Female | D23: Junior Child Care Worker | F23: 34243 | G23: 35862 | H23: =G23* IF(D23<>"Volunteer Carer", VLOOKUP(D23,EmployerSuper,2,FALSE),0) -> 3406.89 | I23: =IF(AND(D23<>"Volunteer Carer",YEARFRAC(DATE(2017,12,31),F23)>=25), VLOOKUP(YEARFRAC(DATE(2017,12,31),F23),EmployeeSuper,2,TRUE)*(G23-J23),0) -> 0 | J23: =VLOOKUP(G23,FixedTax,2,TRUE) +((G23-VLOOKUP(G23,IncomeThreshold,1,TRUE)) * VLOOKUP(G23,TaxPercentage,3,TRUE)) -> 3355.78 | K23: =IF(AND(G23>55874,E23=TRUE), VLOOKUP(G23,HELP,2,TRUE), 0) *G23 -> 0 | L23: =(G23+H23)-(I23+J23) -> 35913.11
A24: Mason | B24: Train | C24: Male | D24: Child Care Worker | F24: 34608 | G24: 45876 | H24: =G24* IF(D24<>"Volunteer Carer", VLOOKUP(D24,EmployerSuper,2,FALSE),0) -> 4358.22 | I24: =IF(AND(D24<>"Volunteer Carer",YEARFRAC(DATE(2017,12,31),F24)>=25), VLOOKUP(YEARFRAC(DATE(2017,12,31),F24),EmployeeSuper,2,TRUE)*(G24-J24),0) -> 0 | J24: =VLOOKUP(G24,FixedTax,2,TRUE) +((G24-VLOOKUP(G24,IncomeThreshold,1,TRUE)) * VLOOKUP(G24,TaxPercentage,3,TRUE)) -> 6456.7 | K24: =IF(AND(G24>55874,E24=TRUE), VLOOKUP(G24,HELP,2,TRUE), 0) *G24 -> 0 | L24: =(G24+H24)-(I24+J24) -> 43777.52
A25: Ashton | B25: Bethel | C25: Male | D25: Accountant | E25: TRUE | F25: 34806 | G25: 55232 | H25: =G25* IF(D25<>"Volunteer Carer", VLOOKUP(D25,EmployerSuper,2,FALSE),0) -> 6075.52 | I25: =IF(AND(D25<>"Volunteer Carer",YEARFRAC(DATE(2017,12,31),F25)>=25), VLOOKUP(YEARFRAC(DATE(2017,12,31),F25),EmployeeSuper,2,TRUE)*(G25-J25),0) -> 0 | J25: =VLOOKUP(G25,FixedTax,2,TRUE) +((G25-VLOOKUP(G25,IncomeThreshold,1,TRUE)) * VLOOKUP(G25,TaxPercentage,3,TRUE)) -> 9497.4 | K25: =IF(AND(G25>55874,E25=TRUE), VLOOKUP(G25,HELP,2,TRUE), 0) *G25 -> 0 | L25: =(G25+H25)-(I25+J25) -> 51810.12
A26: Harry | B26: Lutwyche | C26: Male | D26: Volunteer Carer | E26: TRUE | F26: 35031 | G26: 0 | H26: =G26* IF(D26<>"Volunteer Carer", VLOOKUP(D26,EmployerSuper,2,FALSE),0) -> 0 | I26: =IF(AND(D26<>"Volunteer Carer",YEARFRAC(DATE(2017,12,31),F26)>=25), VLOOKUP(YEARFRAC(DATE(2017,12,31),F26),EmployeeSuper,2,TRUE)*(G26-J26),0) -> 0 | J26: =VLOOKUP(G26,FixedTax,2,TRUE) +((G26-VLOOKUP(G26,IncomeThreshold,1,TRUE)) * VLOOKUP(G26,TaxPercentage,3,TRUE)) -> 0 | K26: =IF(AND(G26>55874,E26=TRUE), VLOOKUP(G26,HELP,2,TRUE), 0) *G26 -> 0 | L26: =(G26+H26)-(I26+J26) -> 0
A27: Victoria | B27: Lamond | C27: Female | D27: Junior Child Care Worker | F27: 35105 | G27: 35862 | H27: =G27* IF(D27<>"Volunteer Carer", VLOOKUP(D27,EmployerSuper,2,FALSE),0) -> 3406.89 | I27: =IF(AND(D27<>"Volunteer Carer",YEARFRAC(DATE(2017,12,31),F27)>=25), VLOOKUP(YEARFRAC(DATE(2017,12,31),F27),EmployeeSuper,2,TRUE)*(G27-J27),0) -> 0 | J27: =VLOOKUP(G27,FixedTax,2,TRUE) +((G27-VLOOKUP(G27,IncomeThreshold,1,TRUE)) * VLOOKUP(G27,TaxPercentage,3,TRUE)) -> 3355.78 | K27: =IF(AND(G27>55874,E27=TRUE), VLOOKUP(G27,HELP,2,TRUE), 0) *G27 -> 0 | L27: =(G27+H27)-(I27+J27) -> 35913.11
A28: Mariam | B28: Betts | C28: Female | D28: Volunteer Carer | E28: TRUE | F28: 35745 | G28: 0 | H28: =G28* IF(D28<>"Volunteer Carer", VLOOKUP(D28,EmployerSuper,2,FALSE),0) -> 0 | I28: =IF(AND(D28<>"Volunteer Carer",YEARFRAC(DATE(2017,12,31),F28)>=25), VLOOKUP(YEARFRAC(DATE(2017,12,31),F28),EmployeeSuper,2,TRUE)*(G28-J28),0) -> 0 | J28: =VLOOKUP(G28,FixedTax,2,TRUE) +((G28-VLOOKUP(G28,IncomeThreshold,1,TRUE)) * VLOOKUP(G28,TaxPercentage,3,TRUE)) -> 0 | K28: =IF(AND(G28>55874,E28=TRUE), VLOOKUP(G28,HELP,2,TRUE), 0) *G28 -> 0 | L28: =(G28+H28)-(I28+J28) -> 0
A29: Sam | B29: Wrenfordsley | C29: Female | D29: Junior Child Care Worker | E29: TRUE | F29: 35838 | G29: 35862 | H29: =G29* IF(D29<>"Volunteer Carer", VLOOKUP(D29,EmployerSuper,2,FALSE),0) -> 3406.89 | I29: =IF(AND(D29<>"Volunteer Carer",YEARFRAC(DATE(2017,12,31),F29)>=25), VLOOKUP(YEARFRAC(DATE(2017,12,31),F29),EmployeeSuper,2,TRUE)*(G29-J29),0) -> 0 | J29: =VLOOKUP(G29,FixedTax,2,TRUE) +((G29-VLOOKUP(G29,IncomeThreshold,1,TRUE)) * VLOOKUP(G29,TaxPercentage,3,TRUE)) -> 3355.78 | K29: =IF(AND(G29>55874,E29=TRUE), VLOOKUP(G29,HELP,2,TRUE), 0) *G29 -> 0 | L29: =(G29+H29)-(I29+J29) -> 35913.11
A30: Harrison | B30: McCallum | C30: Male | D30: Junior Child Care Worker | E30: TRUE | F30: 36257 | G30: 35862 | H30: =G30* IF(D30<>"Volunteer Carer", VLOOKUP(D30,EmployerSuper,2,FALSE),0) -> 3406.89 | I30: =IF(AND(D30<>"Volunteer Carer",YEARFRAC(DATE(2017,12,31),F30)>=25), VLOOKUP(YEARFRAC(DATE(2017,12,31),F30),EmployeeSuper,2,TRUE)*(G30-J30),0) -> 0 | J30: =VLOOKUP(G30,FixedTax,2,TRUE) +((G30-VLOOKUP(G30,IncomeThreshold,1,TRUE)) * VLOOKUP(G30,TaxPercentage,3,TRUE)) -> 3355.78 | K30: =IF(AND(G30>55874,E30=TRUE), VLOOKUP(G30,HELP,2,TRUE), 0) *G30 -> 0 | L30: =(G30+H30)-(I30+J30) -> 35913.11

Sheet Children
A1: Sunshine Children
A2: Child Code | B2: Family Code | C2: Given Name | D2: Family Name | E2: Gender | F2: DOB | G2: Days | H2: Age | I2: Initial Room | J2: Final Room | K2: Number of Days | L2: Weekday String | M2: Weekday Cost Pre Birthday | N2: Saturday Cost Pre Birthday | O2: Weekday Cost Post Birthday | P2: Saturday Cost Post Birthday | Q2: Annual Cost
K3: >=5
M6: Weekday Cost Pre Birthday | N6: Saturday Cost Pre Birthday | O6: Weekday Cost Post Birthday | P6: Saturday Cost Post Birthday | Q6: Annual Cost
L7: Total | M7: =DSUM(_xlnm.Database,M12,_xlnm.Criteria) -> 308280 | N7: =DSUM(_xlnm.Database,N12,_xlnm.Criteria) -> 79505 | O7: =DSUM(_xlnm.Database,O12,_xlnm.Criteria) -> 252760 | P7: =DSUM(_xlnm.Database,P12,_xlnm.Criteria) -> 66120 | Q7: =DSUM(_xlnm.Database,Q12,_xlnm.Criteria) -> 706665
L8: Minimum | M8: =DMIN(_xlnm.Database,M12,_xlnm.Criteria) -> 1955 | N8: =DMIN(_xlnm.Database,N12,_xlnm.Criteria) -> 0 | O8: =DMIN(_xlnm.Database,O12,_xlnm.Criteria) -> 0 | P8: =DMIN(_xlnm.Database,P12,_xlnm.Criteria) -> 0 | Q8: =DMIN(_xlnm.Database,Q12,_xlnm.Criteria) -> 18450
L9: Average | M9: =DAVERAGE(_xlnm.Database,M12,_xlnm.Criteria) -> 11010 | N9: =DAVERAGE(_xlnm.Database,N12,_xlnm.Criteria) -> 2839.4643 | O9: =DAVERAGE(_xlnm.Database,O12,_xlnm.Criteria) -> 9027.1429 | P9: =DAVERAGE(_xlnm.Database,P12,_xlnm.Criteria) -> 2361.4286 | Q9: =DAVERAGE(_xlnm.Database,Q12,_xlnm.Criteria) -> 25238.036
L10: Maximum | M10: =DMAX(_xlnm.Database,M12,_xlnm.Criteria) -> 21360 | N10: =DMAX(_xlnm.Database,N12,_xlnm.Criteria) -> 5850 | O10: =DMAX(_xlnm.Database,O12,_xlnm.Criteria) -> 23430 | P10: =DMAX(_xlnm.Database,P12,_xlnm.Criteria) -> 5290 | Q10: =DMAX(_xlnm.Database,Q12,_xlnm.Criteria) -> 38390
A12: Child Code | B12: Family Code | C12: Given Name | D12: Family Name | E12: Gender | F12: DOB | G12: Days | H12: Age | I12: Initial Room | J12: Final Room | K12: Number of Days | L12: Weekday String | M12: Weekday Cost Pre Birthday | N12: Saturday Cost Pre Birthday | O12: Weekday Cost Post Birthday | P12: Saturday Cost Post Birthday | Q12: Annual Cost
A13: allman-03-05 | B13: allman-03 | C13: Molly | D13: Allman | E13: Female | F13: 41455 | G13: mon,tues,sat | H13: =_xlfn.FLOOR.MATH(YEARFRAC(DATE(2018,1,1),F13)) -> 4 | I13: =IF(H13<6,VLOOKUP(H13,Rooms,2,TRUE),"NOT ALLOWED") -> Kangaroo Room | J13: =IF(H13+1<6,VLOOKUP(H13+1,Rooms,2,TRUE),"NOT ALLOWED") -> Kangaroo Room | K13: =IF(ISNUMBER(SEARCH("mon",G13)),1,0) + IF(ISNUMBER(SEARCH("tues",G13)),1,0) + IF(ISNUMBER(SEARCH("wed",G13)),1,0) + IF(ISNUMBER(SEARCH("thurs",G13)),1,0) + IF(ISNUMBER(SEARCH("fri",G13)),1,0) + IF(ISNUMBER(SEARCH("sat",G13)),1,0) + IF(ISNUMBER(SEARCH("sun",G13)),1,0) -> 3 | L13: =IF(ISNUMBER(SEARCH("mon",G13)),0,1) & IF(ISNUMBER(SEARCH("tues",G13)),0,1) & IF(ISNUMBER(SEARCH("wed",G13)),0,1) & IF(ISNUMBER(SEARCH("thurs",G13)),0,1) & IF(ISNUMBER(SEARCH("fri",G13)),0,1) & 1 & 1 -> 0011111 | M13: =IF(H13<6, (NETWORKDAYS.INTL(DATE(2018,1,1),DATE(2018,MONTH(F13),DAY(F13)),L13,Holidays)) * VLOOKUP(H13,CareCosts,2), 0) -> 4165 | N13: =IF(H13<6, (NETWORKDAYS.INTL(DATE(2018,1,1),DATE(2018,MONTH(F13),DAY(F13)),IF(ISNUMBER(SEARCH("sat",G13)),"1111101","1111111"),Holidays)) * (VLOOKUP(H13,CareCosts,2)+ SaturdayPenalty), 0) -> 2375 | O13: =IF(H13+1<6, (NETWORKDAYS.INTL(DATE(2018,MONTH(F13),DAY(F13)),DATE(2018,12,31),L13,Holidays)) * VLOOKUP(H13+1,CareCosts,2),0) -> 4080 | P13: =IF(H13+1<6, (NETWORKDAYS.INTL(DATE(2018,1,1),DATE(2018,MONTH(F13),DAY(F13)),IF(ISNUMBER(SEARCH("sat",G13)),"1111101","1111111"),Holidays)) * (VLOOKUP(H13+1,CareCosts,2)+ SaturdayPenalty), 0) -> 2250 | Q13: =SUM(M13,N13,O13,P13) -> 12870
A14: allman-03-04 | B14: allman-03 | C14: Regina | D14: Allman | E14: Female | F14: 41921 | G14: mon,tues,sat | H14: =_xlfn.FLOOR.MATH(YEARFRAC(DATE(2018,1,1),F14)) -> 3 | I14: =IF(H14<6,VLOOKUP(H14,Rooms,2,TRUE),"NOT ALLOWED") -> Koala Room | J14: =IF(H14+1<6,VLOOKUP(H14+1,Rooms,2,TRUE),"NOT ALLOWED") -> Kangaroo Room | K14: =IF(ISNUMBER(SEARCH("mon",G14)),1,0) + IF(ISNUMBER(SEARCH("tues",G14)),1,0) + IF(ISNUMBER(SEARCH("wed",G14)),1,0) + IF(ISNUMBER(SEARCH("thurs",G14)),1,0) + IF(ISNUMBER(SEARCH("fri",G14)),1,0) + IF(ISNUMBER(SEARCH("sat",G14)),1,0) + IF(ISNUMBER(SEARCH("sun",G14)),1,0) -> 3 | L14: =IF(ISNUMBER(SEARCH("mon",G14)),0,1) & IF(ISNUMBER(SEARCH("tues",G14)),0,1) & IF(ISNUMBER(SEARCH("wed",G14)),0,1) & IF(ISNUMBER(SEARCH("thurs",G14)),0,1) & IF(ISNUMBER(SEARCH("fri",G14)),0,1) & 1 & 1 -> 0011111 | M14: =IF(H14<6, (NETWORKDAYS.INTL(DATE(2018,1,1),DATE(2018,MONTH(F14),DAY(F14)),L14,Holidays)) * VLOOKUP(H14,CareCosts,2), 0) -> 7020 | N14: =IF(H14<6, (NETWORKDAYS.INTL(DATE(2018,1,1),DATE(2018,MONTH(F14),DAY(F14)+1),IF(ISNUMBER(SEARCH("sat",G14)),"1111101","1111111"),Holidays)) * (VLOOKUP(H14,CareCosts,2)+ SaturdayPenalty), 0) -> 3900 | O14: =IF(H14+1<6, (NETWORKDAYS.INTL(DATE(2018,MONTH(F14),DAY(F14)),DATE(2018,12,31),L14,Holidays)) * VLOOKUP(H14+1,CareCosts,2),0) -> 1955 | P14: =IF(H14+1<6, (NETWORKDAYS.INTL(DATE(2018,1,1),DATE(2018,MONTH(F14),DAY(F14)),IF(ISNUMBER(SEARCH("sat",G14)),"1111101","1111111"),Holidays)) * (VLOOKUP(H14+1,CareCosts,2)+ SaturdayPenalty), 0) -> 3705 | Q14: =SUM(M14,N14,O14,P14) -> 16580
A15: allman-03-03 | B15: allman-03 | C15: Roxanne | D15: Allman | E15: Female | F15: 42310 | G15: mon,tues,sat | H15: =_xlfn.FLOOR.MATH(YEARFRAC(DATE(2018,1,1),F15)) -> 2 | I15: =IF(H15<6,VLOOKUP(H15,Rooms,2,TRUE),"NOT ALLOWED") -> Emu Room | J15: =IF(H15+1<6,VLOOKUP(H15+1,Rooms,2,TRUE),"NOT ALLOWED") -> Koala Room | K15: =IF(ISNUMBER(SEARCH("mon",G15)),1,0) + IF(ISNUMBER(SEARCH("tues",G15)),1,0) + IF(ISNUMBER(SEARCH("wed",G15)),1,0) + IF(ISNUMBER(SEARCH("thurs",G15)),1,0) + IF(ISNUMBER(SEARCH("fri",G15)),1,0) + IF(ISNUMBER(SEARCH("sat",G15)),1,0) + IF(ISNUMBER(SEARCH("sun",G15)),1,0) -> 3 | L15: =IF(ISNUMBER(SEARCH("mon",G15)),0,1) & IF(ISNUMBER(SEARCH("tues",G15)),0,1) & IF(ISNUMBER(SEARCH("wed",G15)),0,1) & IF(ISNUMBER(SEARCH("thurs",G15)),0,1) & IF(ISNUMBER(SEARCH("fri",G15)),0,1) & 1 & 1 -> 0011111 | M15: =IF(H15<6, (NETWORKDAYS.INTL(DATE(2018,1,1),DATE(2018,MONTH(F15),DAY(F15)),L15,Holidays)) * VLOOKUP(H15,CareCosts,2), 0) -> 8820 | N15: =IF(H15<6, (NETWORKDAYS.INTL(DATE(2018,1,1),DATE(2018,MONTH(F15),DAY(F15)+1),IF(ISNUMBER(SEARCH("sat",G15)),"1111101","1111111"),Holidays)) * (VLOOKUP(H15,CareCosts,2)+ SaturdayPenalty), 0) -> 4945 | O15: =IF(H15+1<6, (NETWORKDAYS.INTL(DATE(2018,MONTH(F15),DAY(F15)),DATE(2018,12,31),L15,Holidays)) * VLOOKUP(H15+1,CareCosts,2),0) -> 1440 | P15: =IF(H15+1<6, (NETWORKDAYS.INTL(DATE(2018,1,1),DATE(2018,MONTH(F15),DAY(F15)),IF(ISNUMBER(SEARCH("sat",G15)),"1111101","1111111"),Holidays)) * (VLOOKUP(H15+1,CareCosts,2)+ SaturdayPenalty), 0) -> 4200 | Q15: =SUM(M15,N15,O15,P15) -> 19405
A16: allman-03-02 | B16: allman-03 | C16: Jeffery | D16: Allman | E16: Male | F16: 43095 | G16: mon,tues,sat | H16: =_xlfn.FLOOR.MATH(YEARFRAC(DATE(2018,1,1),F16)) -> 0 | I16: =IF(H16<6,VLOOKUP(H16,Rooms,2,TRUE),"NOT ALLOWED") -> Platypus Room | J16: =IF(H16+1<6,VLOOKUP(H16+1,Rooms,2,TRUE),"NOT ALLOWED") -> Platypus Room | K16: =IF(ISNUMBER(SEARCH("mon",G16)),1,0) + IF(ISNUMBER(SEARCH("tues",G16)),1,0) + IF(ISNUMBER(SEARCH("wed",G16)),1,0) + IF(ISNUMBER(SEARCH("thurs",G16)),1,0) + IF(ISNUMBER(SEARCH("fri",G16)),1,0) + IF(ISNUMBER(SEARCH("sat",G16)),1,0) + IF(ISNUMBER(SEARCH("sun",G16)),1,0) -> 3 | L16: =IF(ISNUMBER(SEARCH("mon",G16)),0,1) & IF(ISNUMBER(SEARCH("tues",G16)),0,1) & IF(ISNUMBER(SEARCH("wed",G16)),0,1) & IF(ISNUMBER(SEARCH("thurs",G16)),0,1) & IF(ISNUMBER(SEARCH("fri",G16)),0,1) & 1 & 1 -> 0011111 | M16: =IF(H16<6, (NETWORKDAYS.INTL(DATE(2018,1,1),DATE(2018,MONTH(F16),DAY(F16)),L16,Holidays)) * VLOOKUP(H16,CareCosts,2), 0) -> 11880 | N16: =IF(H16<6, (NETWORKDAYS.INTL(DATE(2018,1,1),DATE(2018,MONTH(F16),DAY(F16)+1),IF(ISNUMBER(SEARCH("sat",G16)),"1111101","1111111"),Holidays)) * (VLOOKUP(H16,CareCosts,2)+ SaturdayPenalty), 0) -> 6500 | O16: =IF(H16+1<6, (NETWORKDAYS.INTL(DATE(2018,MONTH(F16),DAY(F16)),DATE(2018,12,31),L16,Holidays)) * VLOOKUP(H16+1,CareCosts,2),0) -> 110 | P16: =IF(H16+1<6, (NETWORKDAYS.INTL(DATE(2018,1,1),DATE(2018,MONTH(F16),DAY(F16)),IF(ISNUMBER(SEARCH("sat",G16)),"1111101","1111111"),Holidays)) * (VLOOKUP(H16+1,CareCosts,2)+ SaturdayPenalty), 0) -> 6000 | Q16: =SUM(M16,N16,O16,P16) -> 24490
A17: barclay-02-02 | B17: barclay-02 | C17: Jennifer | D17: Barclay | E17: Female | F17: 42785 | G17: tues,wed | H17: =_xlfn.FLOOR.MATH(YEARFRAC(DATE(2018,1,1),F17)) -> 0 | I17: =IF(H17<6,VLOOKUP(H17,Rooms,2,TRUE),"NOT ALLOWED") -> Platypus Room | J17: =IF(H17+1<6,VLOOKUP(H17+1,Rooms,2,TRUE),"NOT ALLOWED") -> Platypus Room | K17: =IF(ISNUMBER(SEARCH("mon",G17)),1,0) + IF(ISNUMBER(SEARCH("tues",G17)),1,0) + IF(ISNUMBER(SEARCH("wed",G17)),1,0) + IF(ISNUMBER(SEARCH("thurs",G17)),1,0) + IF(ISNUMBER(SEARCH("fri",G17)),1,0) + IF(ISNUMBER(SEARCH("sat",G17)),1,0) + IF(ISNUMBER(SEARCH("sun",G17)),1,0) -> 2 | L17: =IF(ISNUMBER(SEARCH("mon",G17)),0,1) & IF(ISNUMBER(SEARCH("tues",G17)),0,1) & IF(ISNUMBER(SEARCH("wed",G17)),0,1) & IF(ISNUMBER(SEARCH("thurs",G17)),0,1) & IF(ISNUMBER(SEARCH("fri",G17)),0,1) & 1 & 1 -> 1001111 | M17: =IF(H17<6, (NETWORKDAYS.INTL(DATE(2018,1,1),DATE(2018,MONTH(F17),DAY(F17)),L17,Holidays)) * VLOOKUP(H17,CareCosts,2), 0) -> 1680 | N17: =IF(H17<6, (NETWORKDAYS.INTL(DATE(2018,1,1),DATE(2018,MONTH(F17),DAY(F17)+1),IF(ISNUMBER(SEARCH("sat",G17)),"1111101","1111111"),Holidays)) * (VLOOKUP(H17,CareCosts,2)+ SaturdayPenalty), 0) -> 0 | O17: =IF(H17+1<6, (NETWORKDAYS.INTL(DATE(2018,MONTH(F17),DAY(F17)),DATE(2018,12,31),L17,Holidays)) * VLOOKUP(H17+1,CareCosts,2),0) -> 9460 | P17: =IF(H17+1<6, (NETWORKDAYS.INTL(DATE(2018,1,1),DATE(2018,MONTH(F17),DAY(F17)),IF(ISNUMBER(SEARCH("sat",G17)),"1111101","1111111"),Holidays)) * (VLOOKUP(H17+1,CareCosts,2)+ SaturdayPenalty), 0) -> 0 | Q17: =SUM(M17,N17,O17,P17) -> 11140
A18: barclay-02-01 | B18: barclay-02 | C18: Robert | D18: Barclay | E18: Male | F18: 42785 | G18: tues,wed | H18: =_xlfn.FLOOR.MATH(YEARFRAC(DATE(2018,1,1),F18)) -> 0 | I18: =IF(H18<6,VLOOKUP(H18,Rooms,2,TRUE),"NOT ALLOWED") -> Platypus Room | J18: =IF(H18+1<6,VLOOKUP(H18+1,Rooms,2,TRUE),"NOT ALLOWED") -> Platypus Room | K18: =IF(ISNUMBER(SEARCH("mon",G18)),1,0) + IF(ISNUMBER(SEARCH("tues",G18)),1,0) + IF(ISNUMBER(SEARCH("wed",G18)),1,0) + IF(ISNUMBER(SEARCH("thurs",G18)),1,0) + IF(ISNUMBER(SEARCH("fri",G18)),1,0) + IF(ISNUMBER(SEARCH("sat",G18)),1,0) + IF(ISNUMBER(SEARCH("sun",G18)),1,0) -> 2 | L18: =IF(ISNUMBER(SEARCH("mon",G18)),0,1) & IF(ISNUMBER(SEARCH("tues",G18)),0,1) & IF(ISNUMBER(SEARCH("wed",G18)),0,1) & IF(ISNUMBER(SEARCH("thurs",G18)),0,1) & IF(ISNUMBER(SEARCH("fri",G18)),0,1) & 1 & 1 -> 1001111 | M18: =IF(H18<6, (NETWORKDAYS.INTL(DATE(2018,1,1),DATE(2018,MONTH(F18),DAY(F18)),L18,Holidays)) * VLOOKUP(H18,CareCosts,2), 0) -> 1680 | N18: =IF(H18<6, (NETWORKDAYS.INTL(DATE(2018,1,1),DATE(2018,MONTH(F18),DAY(F18)+1),IF(ISNUMBER(SEARCH("sat",G18)),"1111101","1111111"),Holidays)) * (VLOOKUP(H18,CareCosts,2)+ SaturdayPenalty), 0) -> 0 | O18: =IF(H18+1<6, (NETWORKDAYS.INTL(DATE(2018,MONTH(F18),DAY(F18)),DATE(2018,12,31),L18,Holidays)) * VLOOKUP(H18+1,CareCosts,2),0) -> 9460 | P18: =IF(H18+1<6, (NETWORKDAYS.INTL(DATE(2018,1,1),DATE(2018,MONTH(F18),DAY(F18)),IF(ISNUMBER(SEARCH("sat",G18)),"1111101","1111111"),Holidays)) * (VLOOKUP(H18+1,CareCosts,2)+ SaturdayPenalty), 0) -> 0 | Q18: =SUM(M18,N18,O18,P18) -> 11140
A19: barnard-02-03 | B19: barnard-02 | C19: Brandon | D19: Barnard | E19: Male | F19: 41980 | G19: fri,sat | H19: =_xlfn.FLOOR.MATH(YEARFRAC(DATE(2018,1,1),F19)) -> 3 | I19: =IF(H19<6,VLOOKUP(H19,Rooms,2,TRUE),"NOT ALLOWED") -> Koala Room | J19: =IF(H19+1<6,VLOOKUP(H19+1,Rooms,2,TRUE),"NOT ALLOWED") -> Kangaroo Room | K19: =IF(ISNUMBER(SEARCH("mon",G19)),1,0) + IF(ISNUMBER(SEARCH("tues",G19)),1,0) + IF(ISNUMBER(SEARCH("wed",G19)),1,0) + IF(ISNUMBER(SEARCH("thurs",G19)),1,0) + IF(ISNUMBER(SEARCH("fri",G19)),1,0) + IF(ISNUMBER(SEARCH("sat",G19)),1,0) + IF(ISNUMBER(SEARCH("sun",G19)),1,0) -> 2 | L19: =IF(ISNUMBER(SEARCH("mon",G19)),0,1) & IF(ISNUMBER(SEARCH("tues",G19)),0,1) & IF(ISNUMBER(SEARCH("wed",G19)),0,1) & IF(ISNUMBER(SEARCH("thurs",G19)),0,1) & IF(ISNUMBER(SEARCH("fri",G19)),0,1) & 1 & 1 -> 1111011 | M19: =IF(H19<6, (NETWORKDAYS.INTL(DATE(2018,1,1),DATE(2018,MONTH(F19),DAY(F19)),L19,Holidays)) * VLOOKUP(H19,CareCosts,2), 0) -> 4230 | N19: =IF(H19<6, (NETWORKDAYS.INTL(DATE(2018,1,1),DATE(2018,MONTH(F19),DAY(F19)+1),IF(ISNUMBER(SEARCH("sat",G19)),"1111101","1111111"),Holidays)) * (VLOOKUP(H19,CareCosts,2)+ SaturdayPenalty), 0) -> 4800 | O19: =IF(H19+1<6, (NETWORKDAYS.INTL(DATE(2018,MONTH(F19),DAY(F19)),DATE(2018,12,31),L19,Holidays)) * VLOOKUP(H19+1,CareCosts,2),0) -> 340 | P19: =IF(H19+1<6, (NETWORKDAYS.INTL(DATE(2018,1,1),DATE(2018,MONTH(F19),DAY(F19)),IF(ISNUMBER(SEARCH("sat",G19)),"1111101","1111111"),Holidays)) * (VLOOKUP(H19+1,CareCosts,2)+ SaturdayPenalty), 0) -> 4465 | Q19: =SUM(M19,N19,O19,P19) -> 13835
A20: barnard-02-04 | B20: barnard-02 | C20: Janis | D20: Barnard | E20: Female | F20: 41980 | G20: fri,sat | H20: =_xlfn.FLOOR.MATH(YEARFRAC(DATE(2018,1,1),F20)) -> 3 | I20: =IF(H20<6,VLOOKUP(H20,Rooms,2,TRUE),"NOT ALLOWED") -> Koala Room | J20: =IF(H20+1<6,VLOOKUP(H20+1,Rooms,2,TRUE),"NOT ALLOWED") -> Kangaroo Room | K20: =IF(ISNUMBER(SEARCH("mon",G20)),1,0) + IF(ISNUMBER(SEARCH("tues",G20)),1,0) + IF(ISNUMBER(SEARCH("wed",G20)),1,0) + IF(ISNUMBER(SEARCH("thurs",G20)),1,0) + IF(ISNUMBER(SEARCH("fri",G20)),1,0) + IF(ISNUMBER(SEARCH("sat",G20)),1,0) + IF(ISNUMBER(SEARCH("sun",G20)),1,0) -> 2 | L20: =IF(ISNUMBER(SEARCH("mon",G20)),0,1) & IF(ISNUMBER(SEARCH("tues",G20)),0,1) & IF(ISNUMBER(SEARCH("wed",G20)),0,1) & IF(ISNUMBER(SEARCH("thurs",G20)),0,1) & IF(ISNUMBER(SEARCH("fri",G20)),0,1) & 1 & 1 -> 1111011 | M20: =IF(H20<6, (NETWORKDAYS.INTL(DATE(2018,1,1),DATE(2018,MONTH(F20),DAY(F20)),L20,Holidays)) * VLOOKUP(H20,CareCosts,2), 0) -> 4230 | N20: =IF(H20<6, (NETWORKDAYS.INTL(DATE(2018,1,1),DATE(2018,MONTH(F20),DAY(F20)+1),IF(ISNUMBER(SEARCH("sat",G20)),"1111101","1111111"),Holidays)) * (VLOOKUP(H20,CareCosts,2)+ SaturdayPenalty), 0) -> 4800 | O20: =IF(H20+1<6, (NETWORKDAYS.INTL(DATE(2018,MONTH(F20),DAY(F20)),DATE(2018,12,31),L20,Holidays)) * VLOOKUP(H20+1,CareCosts,2),0) -> 340 | P20: =IF(H20+1<6, (NETWORKDAYS.INTL(DATE(2018,1,1),DATE(2018,MONTH(F20),DAY(F20)),IF(ISNUMBER(SEARCH("sat",G20)),"1111101","1111111"),Holidays)) * (VLOOKUP(H20+1,CareCosts,2)+ SaturdayPenalty), 0) -> 4465 | Q20: =SUM(M20,N20,O20,P20) -> 13835
A21: barnard-02-02 | B21: barnard-02 | C21: Madeline | D21: Barnard | E21: Female | F21: 41980 | G21: fri,sat | H21: =_xlfn.FLOOR.MATH(YEARFRAC(DATE(2018,1,1),F21)) -> 3 | I21: =IF(H21<6,VLOOKUP(H21,Rooms,2,TRUE),"NOT ALLOWED") -> Koala Room | J21: =IF(H21+1<6,VLOOKUP(H21+1,Rooms,2,TRUE),"NOT ALLOWED") -> Kangaroo Room | K21: =IF(ISNUMBER(SEARCH("mon",G21)),1,0) + IF(ISNUMBER(SEARCH("tues",G21)),1,0) + IF(ISNUMBER(SEARCH("wed",G21)),1,0) + IF(ISNUMBER(SEARCH("thurs",G21)),1,0) + IF(ISNUMBER(SEARCH("fri",G21)),1,0) + IF(ISNUMBER(SEARCH("sat",G21)),1,0) + IF(ISNUMBER(SEARCH("sun",G21)),1,0) -> 2 | L21: =IF(ISNUMBER(SEARCH("mon",G21)),0,1) & IF(ISNUMBER(SEARCH("tues",G21)),0,1) & IF(ISNUMBER(SEARCH("wed",G21)),0,1) & IF(ISNUMBER(SEARCH("thurs",G21)),0,1) & IF(ISNUMBER(SEARCH("fri",G21)),0,1) & 1 & 1 -> 1111011 | M21: =IF(H21<6, (NETWORKDAYS.INTL(DATE(2018,1,1),DATE(2018,MONTH(F21),DAY(F21)),L21,Holidays)) * VLOOKUP(H21,CareCosts,2), 0) -> 4230 | N21: =IF(H21<6, (NETWORKDAYS.INTL(DATE(2018,1,1),DATE(2018,MONTH(F21),DAY(F21)+1),IF(ISNUMBER(SEARCH("sat",G21)),"1111101","1111111"),Holidays)) * (VLOOKUP(H21,CareCosts,2)+ SaturdayPenalty), 0) -> 4800 | O21: =IF(H21+1<6, (NETWORKDAYS.INTL(DATE(2018,MONTH(F21),DAY(F21)),DATE(2018,12,31),L21,Holidays)) * VLOOKUP(H21+1,CareCosts,2),0) -> 340 | P21: =IF(H21+1<6, (NETWORKDAYS.INTL(DATE(2018,1,1),DATE(2018,MONTH(F21),DAY(F21)),IF(ISNUMBER(SEARCH("sat",G21)),"1111101","1111111"),Holidays)) * (VLOOKUP(H21+1,CareCosts,2)+ SaturdayPenalty), 0) -> 4465 | Q21: =SUM(M21,N21,O21,P21) -> 13835
A22: barnard-02-05 | B22: barnard-02 | C22: Robert | D22: Barnard | E22: Male | F22: 41980 | G22: fri,sat | H22: =_xlfn.FLOOR.MATH(YEARFRAC(DATE(2018,1,1),F22)) -> 3 | I22: =IF(H22<6,VLOOKUP(H22,Rooms,2,TRUE),"NOT ALLOWED") -> Koala Room | J22: =IF(H22+1<6,VLOOKUP(H22+1,Rooms,2,TRUE),"NOT ALLOWED") -> Kangaroo Room | K22: =IF(ISNUMBER(SEARCH("mon",G22)),1,0) + IF(ISNUMBER(SEARCH("tues",G22)),1,0) + IF(ISNUMBER(SEARCH("wed",G22)),1,0) + IF(ISNUMBER(SEARCH("thurs",G22)),1,0) + IF(ISNUMBER(SEARCH("fri",G22)),1,0) + IF(ISNUMBER(SEARCH("sat",G22)),1,0) + IF(ISNUMBER(SEARCH("sun",G22)),1,0) -> 2 | L22: =IF(ISNUMBER(SEARCH("mon",G22)),0,1) & IF(ISNUMBER(SEARCH("tues",G22)),0,1) & IF(ISNUMBER(SEARCH("wed",G22)),0,1) & IF(ISNUMBER(SEARCH("thurs",G22)),0,1) & IF(ISNUMBER(SEARCH("fri",G22)),0,1) & 1 & 1 -> 1111011 | M22: =IF(H22<6, (NETWORKDAYS.INTL(DATE(2018,1,1),DATE(2018,MONTH(F22),DAY(F22)),L22,Holidays)) * VLOOKUP(H22,CareCosts,2), 0) -> 4230 | N22: =IF(H22<6, (NETWORKDAYS.INTL(DATE(2018,1,1),DATE(2018,MONTH(F22),DAY(F22)+1),IF(ISNUMBER(SEARCH("sat",G22)),"1111101","1111111"),Holidays)) * (VLOOKUP(H22,CareCosts,2)+ SaturdayPenalty), 0) -> 4800 | O22: =IF(H22+1<6, (NETWORKDAYS.INTL(DATE(2018,MONTH(F22),DAY(F22)),DATE(2018,12,31),L22,Holidays)) * VLOOKUP(H22+1,CareCosts,2),0) -> 340 | P22: =IF(H22+1<6, (NETWORKDAYS.INTL(DATE(2018,1,1),DATE(2018,MONTH(F22),DAY(F22)),IF(ISNUMBER(SEARCH("sat",G22)),"1111101","1111111"),Holidays)) * (VLOOKUP(H22+1,CareCosts,2)+ SaturdayPenalty), 0) -> 4465 | Q22: =SUM(M22,N22,O22,P22) -> 13835
A23: bernardini-02-01 | B23: bernardini-02 | C23: Heath | D23: Bernardini | E23: Male | F23: 42703 | G23: tues,wed,thurs,fri,sat | H23: =_xlfn.FLOOR.MATH(YEARFRAC(DATE(2018,1,1),F23)) -> 1 | I23: =IF(H23<6,VLOOKUP(H23,Rooms,2,TRUE),"NOT ALLOWED") -> Platypus Room | J23: =IF(H23+1<6,VLOOKUP(H23+1,Rooms,2,TRUE),"NOT ALLOWED") -> Emu Room | K23: =IF(ISNUMBER(SEARCH("mon",G23)),1,0) + IF(ISNUMBER(SEARCH("tues",G23)),1,0) + IF(ISNUMBER(SEARCH("wed",G23)),1,0) + IF(ISNUMBER(SEARCH("thurs",G23)),1,0) + IF(ISNUMBER(SEARCH("fri",G23)),1,0) + IF(ISNUMBER(SEARCH("sat",G23)),1,0) + IF(ISNUMBER(SEARCH("sun",G23)),1,0) -> 5 | L23: =IF(ISNUMBER(SEARCH("mon",G23)),0,1) & IF(ISNUMBER(SEARCH("tues",G23)),0,1) & IF(ISNUMBER(SEARCH("wed",G23)),0,1) & IF(ISNUMBER(SEARCH("thurs",G23)),0,1) & IF(ISNUMBER(SEARCH("fri",G23)),0,1) & 1 & 1 -> 1000011 | M23: =IF(H23<6, (NETWORKDAYS.INTL(DATE(2018,1,1),DATE(2018,MONTH(F23),DAY(F23)),L23,Holidays)) * VLOOKUP(H23,CareCosts,2), 0) -> 20570 | N23: =IF(H23<6, (NETWORKDAYS.INTL(DATE(2018,1,1),DATE(2018,MONTH(F23),DAY(F23)+1),IF(ISNUMBER(SEARCH("sat",G23)),"1111101","1111111"),Holidays)) * (VLOOKUP(H23,CareCosts,2)+ SaturdayPenalty), 0) -> 5520 | O23: =IF(H23+1<6, (NETWORKDAYS.INTL(DATE(2018,MONTH(F23),DAY(F23)),DATE(2018,12,31),L23,Holidays)) * VLOOKUP(H23+1,CareCosts,2),0) -> 1680 | P23: =IF(H23+1<6, (NETWORKDAYS.INTL(DATE(2018,1,1),DATE(2018,MONTH(F23),DAY(F23)),IF(ISNUMBER(SEARCH("sat",G23)),"1111101","1111111"),Holidays)) * (VLOOKUP(H23+1,CareCosts,2)+ SaturdayPenalty), 0) -> 5290 | Q23: =SUM(M23,N23,O23,P23) -> 33060
A24: bruner-03-01 | B24: bruner-03 | C24: Jonas | D24: Bruner | E24: Male | F24: 41772 | G24: mon,tues,wed,sat | H24: =_xlfn.FLOOR.MATH(YEARFRAC(DATE(2018,1,1),F24)) -> 3 | I24: =IF(H24<6,VLOOKUP(H24,Rooms,2,TRUE),"NOT ALLOWED") -> Koala Room | J24: =IF(H24+1<6,VLOOKUP(H24+1,Rooms,2,TRUE),"NOT ALLOWED") -> Kangaroo Room | K24: =IF(ISNUMBER(SEARCH("mon",G24)),1,0) + IF(ISNUMBER(SEARCH("tues",G24)),1,0) + IF(ISNUMBER(SEARCH("wed",G24)),1,0) + IF(ISNUMBER(SEARCH("thurs",G24)),1,0) + IF(ISNUMBER(SEARCH("fri",G24)),1,0) + IF(ISNUMBER(SEARCH("sat",G24)),1,0) + IF(ISNUMBER(SEARCH("sun",G24)),1,0) -> 4 | L24: =IF(ISNUMBER(SEARCH("mon",G24)),0,1) & IF(ISNUMBER(SEARCH("tues",G24)),0,1) & IF(ISNUMBER(SEARCH("wed",G24)),0,1) & IF(ISNUMBER(SEARCH("thurs",G24)),0,1) & IF(ISNUMBER(SEARCH("fri",G24)),0,1) & 1 & 1 -> 0001111 | M24: =IF(H24<6, (NETWORKDAYS.INTL(DATE(2018,1,1),DATE(2018,MONTH(F24),DAY(F24)),L24,Holidays)) * VLOOKUP(H24,CareCosts,2), 0) -> 4770 | N24: =IF(H24<6, (NETWORKDAYS.INTL(DATE(2018,1,1),DATE(2018,MONTH(F24),DAY(F24)+1),IF(ISNUMBER(SEARCH("sat",G24)),"1111101","1111111"),Holidays)) * (VLOOKUP(H24,CareCosts,2)+ SaturdayPenalty), 0) -> 1800 | O24: =IF(H24+1<6, (NETWORKDAYS.INTL(DATE(2018,MONTH(F24),DAY(F24)),DATE(2018,12,31),L24,Holidays)) * VLOOKUP(H24+1,CareCosts,2),0) -> 8160 | P24: =IF(H24+1<6, (NETWORKDAYS.INTL(DATE(2018,1,1),DATE(2018,MONTH(F24),DAY(F24)),IF(ISNUMBER(SEARCH("sat",G24)),"1111101","1111111"),Holidays)) * (VLOOKUP(H24+1,CareCosts,2)+ SaturdayPenalty), 0) -> 1710 | Q24: =SUM(M24,N24,O24,P24) -> 16440
A25: burke-02-02 | B25: burke-02 | C25: Micael | D25: Burke | E25: Male | F25: 42061 | G25: tues,thurs,fri,sat | H25: =_xlfn.FLOOR.MATH(YEARFRAC(DATE(2018,1,1),F25)) -> 2 | I25: =IF(H25<6,VLOOKUP(H25,Rooms,2,TRUE),"NOT ALLOWED") -> Emu Room | J25: =IF(H25+1<6,VLOOKUP(H25+1,Rooms,2,TRUE),"NOT ALLOWED") -> Koala Room | K25: =IF(ISNUMBER(SEARCH("mon",G25)),1,0) + IF(ISNUMBER(SEARCH("tues",G25)),1,0) + IF(ISNUMBER(SEARCH("wed",G25)),1,0) + IF(ISNUMBER(SEARCH("thurs",G25)),1,0) + IF(ISNUMBER(SEARCH("fri",G25)),1,0) + IF(ISNUMBER(SEARCH("sat",G25)),1,0) + IF(ISNUMBER(SEARCH("sun",G25)),1,0) -> 4 | L25: =IF(ISNUMBER(SEARCH("mon",G25)),0,1) & IF(ISNUMBER(SEARCH("tues",G25)),0,1) & IF(ISNUMBER(SEARCH("wed",G25)),0,1) & IF(ISNUMBER(SEARCH("thurs",G25)),0,1) & IF(ISNUMBER(SEARCH("fri",G25)),0,1) & 1 & 1 -> 1010011 | M25: =IF(H25<6, (NETWORKDAYS.INTL(DATE(2018,1,1),DATE(2018,MONTH(F25),DAY(F25)),L25,Holidays)) * VLOOKUP(H25,CareCosts,2), 0) -> 2415 | N25: =IF(H25<6, (NETWORKDAYS.INTL(DATE(2018,1,1),DATE(2018,MONTH(F25),DAY(F25)+1),IF(ISNUMBER(SEARCH("sat",G25)),"1111101","1111111"),Holidays)) * (VLOOKUP(H25,CareCosts,2)+ SaturdayPenalty), 0) -> 920 | O25: =IF(H25+1<6, (NETWORKDAYS.INTL(DATE(2018,MONTH(F25),DAY(F25)),DATE(2018,12,31),L25,Holidays)) * VLOOKUP(H25+1,CareCosts,2),0) -> 11700 | P25: =IF(H25+1<6, (NETWORKDAYS.INTL(DATE(2018,1,1),DATE(2018,MONTH(F25),DAY(F25)),IF(ISNUMBER(SEARCH("sat",G25)),"1111101","1111111"),Holidays)) * (VLOOKUP(H25+1,CareCosts,2)+ SaturdayPenalty), 0) -> 800 | Q25: =SUM(M25,N25,O25,P25) -> 15835
... A128: yost-02-05 | B128: yost-02 | C128: Angelica | D128: Yost | E128: Female | F128: 43055 | G128: mon,tues,thurs,fri,sat | H128: =_xlfn.FLOOR.MATH(YEARFRAC(DATE(2018,1,1),F128)) -> 0 | I128: =IF(H128<6,VLOOKUP(H128,Rooms,2,TRUE),"NOT ALLOWED") -> Platypus Room | J128: =IF(H128+1<6,VLOOKUP(H128+1,Rooms,2,TRUE),"NOT ALLOWED") -> Platypus Room | K128: =IF(ISNUMBER(SEARCH("mon",G128)),1,0) + IF(ISNUMBER(SEARCH("tues",G128)),1,0) + IF(ISNUMBER(SEARCH("wed",G128)),1,0) + IF(ISNUMBER(SEARCH("thurs",G128)),1,0) + IF(ISNUMBER(SEARCH("fri",G128)),1,0) + IF(ISNUMBER(SEARCH("sat",G128)),1,0) + IF(ISNUMBER(SEARCH("sun",G128)),1,0) -> 5 | L128: =IF(ISNUMBER(SEARCH("mon",G128)),0,1) & IF(ISNUMBER(SEARCH("tues",G128)),0,1) & IF(ISNUMBER(SEARCH("wed",G128)),0,1) & IF(ISNUMBER(SEARCH("thurs",G128)),0,1) & IF(ISNUMBER(SEARCH("fri",G128)),0,1) & 1 & 1 -> 0010011 | M128: =IF(H128<6, (NETWORKDAYS.INTL(DATE(2018,1,1),DATE(2018,MONTH(F128),DAY(F128)),L128,Holidays)) * VLOOKUP(H128,CareCosts,2), 0) -> 21360 | N128: =IF(H128<6, (NETWORKDAYS.INTL(DATE(2018,1,1),DATE(2018,MONTH(F128),DAY(F128)+1),IF(ISNUMBER(SEARCH("sat",G128)),"1111101","1111111"),Holidays)) * (VLOOKUP(H128,CareCosts,2)+ SaturdayPenalty), 0) -> 5850 | O128: =IF(H128+1<6, (NETWORKDAYS.INTL(DATE(2018,MONTH(F128),DAY(F128)),DATE(2018,12,31),L128,Holidays)) * VLOOKUP(H128+1,CareCosts,2),0) -> 2750 | P128: =IF(H128+1<6, (NETWORKDAYS.INTL(DATE(2018,1,1),DATE(2018,MONTH(F128),DAY(F128)),IF(ISNUMBER(SEARCH("sat",G128)),"1111101","1111111"),Holidays)) * (VLOOKUP(H128+1,CareCosts,2)+ SaturdayPenalty), 0) -> 5280 | Q128: =SUM(M128,N128,O128,P128) -> 35240

Sheet ChildrenPivotTable
A3: Initial Number of Male and Female in Sunshine Childcare Rooms
A4: Initial Room | B4: Female | C4: Male | D4: Grand Total
A5: Emu Room | B5: 15 | C5: 16 | D5: 31
A6: 2 | B6: 15 | C6: 16 | D6: 31
A7: Kangaroo Room | B7: 11 | C7: 17 | D7: 28
A8: 4 | B8: 10 | C8: 15 | D8: 25
A9: 5 | B9: 1 | C9: 2 | D9: 3
A10: Koala Room | B10: 13 | C10: 19 | D10: 32
A11: 3 | B11: 13 | C11: 19 | D11: 32
A12: Platypus Room | B12: 12 | C12: 13 | D12: 25
A13: 0 | B13: 6 | C13: 7 | D13: 13
A14: 1 | B14: 6 | C14: 6 | D14: 12
A15: Grand Total | B15: 51 | C15: 65 | D15: 116

Sheet Families
A1: Sunshine Families
A2: Family Code | B2: Family Name | C2: Parent/Guardian 1 Given Name | D2: Parent/Guardian 1 Family Name | E2: Parent/Guardian 2 Given Name | F2: Parent/Guardian 2 Family Name | G2: Family Income | H2: Number of Children | I2: Weekly Hours | J2: Annual Cost | K2: Annual CCB | L2: Annual CCR | M2: Annual Payable
A3: allman-03 | B3: Allman | C3: Jessica | D3: Allman | E3: Grant | F3: Allman | G3: 116538 | H3: =COUNTIF(Children!$B$13:$B$128,A3) -> 4 | I3: =10*SUMIFS(Children!$K$13:$K$128,Children!$B$13:$B$128,Families!A3) -> 120 | J3: =SUMIFS(Children!$Q$13:$Q$128,Children!$B$13:$B$128,Families!A3) -> 73345 | K3: =MAX(0,IF(G3<CCBThreshold, IF(I3/H3<CCBMaxHours, I3*52*CCBHourlyRate, 50*52*CCBHourlyRate ), IF(I3/H3<CCBMaxHours, I3*52*(CCBHourlyRate-(G3-CCBThreshold)*CCBThresholdModifier), 50*52*(CCBHourlyRate-(G3-CCBThreshold)*CCBThresholdModifier) ) )) -> 1589.6026 | L3: =MIN((J3-K3) * CCRRate, (CCRMax*H3)) -> 30452 | M3: =J3-(K3+L3) -> 41303.397
A4: barclay-02 | B4: Barclay | C4: Lucas | D4: Barclay | E4: Rosalie | F4: Barclay | G4: 117463 | H4: =COUNTIF(Children!$B$13:$B$128,A4) -> 2 | I4: =10*SUMIFS(Children!$K$13:$K$128,Children!$B$13:$B$128,Families!A4) -> 40 | J4: =SUMIFS(Children!$Q$13:$Q$128,Children!$B$13:$B$128,Families!A4) -> 22280 | K4: =MAX(0,IF(G4<CCBThreshold, IF(I4/H4<CCBMaxHours, I4*52*CCBHourlyRate, 50*52*CCBHourlyRate ), IF(I4/H4<50, I4*52*(CCBHourlyRate-(G4-CCBThreshold)*CCBThresholdModifier), 50*52*(CCBHourlyRate-(G4-CCBThreshold)*CCBThresholdModifier) ) )) -> 517.36152 | L4: =MIN((J4-K4) * CCRRate, (CCRMax*H4)) -> 10881.319 | M4: =J4-(K4+L4) -> 10881.319
A5: barnard-02 | B5: Barnard | C5: Mitchell | D5: Barnard | E5: Bethany | F5: Abrahamsson | G5: 191401 | H5: =COUNTIF(Children!$B$13:$B$128,A5) -> 4 | I5: =10*SUMIFS(Children!$K$13:$K$128,Children!$B$13:$B$128,Families!A5) -> 80 | J5: =SUMIFS(Children!$Q$13:$Q$128,Children!$B$13:$B$128,Families!A5) -> 55340 | K5: =MAX(0,IF(G5<CCBThreshold, IF(I5/H5<CCBMaxHours, I5*52*CCBHourlyRate, 50*52*CCBHourlyRate ), IF(I5/H5<50, I5*52*(CCBHourlyRate-(G5-CCBThreshold)*CCBThresholdModifier), 50*52*(CCBHourlyRate-(G5-CCBThreshold)*CCBThresholdModifier) ) )) -> 0 | L5: =MIN((J5-K5) * CCRRate, (CCRMax*H5)) -> 27670 | M5: =J5-(K5+L5) -> 27670
A6: bernardini-02 | B6: Bernardini | C6: Hiram | D6: Bernardini | E6: Heather | F6: Bernardini | G6: 72685 | H6: =COUNTIF(Children!$B$13:$B$128,A6) -> 1 | I6: =10*SUMIFS(Children!$K$13:$K$128,Children!$B$13:$B$128,Families!A6) -> 50 | J6: =SUMIFS(Children!$Q$13:$Q$128,Children!$B$13:$B$128,Families!A6) -> 33060 | K6: =MAX(0,IF(G6<CCBThreshold, IF(I6/H6<CCBMaxHours, I6*52*CCBHourlyRate, 50*52*CCBHourlyRate ), IF(I6/H6<50, I6*52*(CCBHourlyRate-(G6-CCBThreshold)*CCBThresholdModifier), 50*52*(CCBHourlyRate-(G6-CCBThreshold)*CCBThresholdModifier) ) )) -> 1403.4501 | L6: =MIN((J6-K6) * CCRRate, (CCRMax*H6)) -> 7613 | M6: =J6-(K6+L6) -> 24043.55
A7: bruner-03 | B7: Bruner | C7: Clarence | D7: Bruner | E7: Jill | F7: Bruner | G7: 85772 | H7: =COUNTIF(Children!$B$13:$B$128,A7) -> 1 | I7: =10*SUMIFS(Children!$K$13:$K$128,Children!$B$13:$B$128,Families!A7) -> 40 | J7: =SUMIFS(Children!$Q$13:$Q$128,Children!$B$13:$B$128,Families!A7) -> 16440 | K7: =MAX(0,IF(G7<CCBThreshold, IF(I7/H7<CCBMaxHours, I7*52*CCBHourlyRate, 50*52*CCBHourlyRate ), IF(I7/H7<50, I7*52*(CCBHourlyRate-(G7-CCBThreshold)*CCBThresholdModifier), 50*52*(CCBHourlyRate-(G7-CCBThreshold)*CCBThresholdModifier) ) )) -> 945.82384 | L7: =MIN((J7-K7) * CCRRate, (CCRMax*H7)) -> 7613 | M7: =J7-(K7+L7) -> 7881.1762
A8: burke-02 | B8: Burke | C8: Don | D8: Burke | E8: Norma | F8: Burke | G8: 168529 | H8: =COUNTIF(Children!$B$13:$B$128,A8) -> 1 | I8: =10*SUMIFS(Children!$K$13:$K$128,Children!$B$13:$B$128,Families!A8) -> 40 | J8: =SUMIFS(Children!$Q$13:$Q$128,Children!$B$13:$B$128,Families!A8) -> 15835 | K8: =MAX(0,IF(G8<CCBThreshold, IF(I8/H8<CCBMaxHours, I8*52*CCBHourlyRate, 50*52*CCBHourlyRate ), IF(I8/H8<50, I8*52*(CCBHourlyRate-(G8-CCBThreshold)*CCBThresholdModifier), 50*52*(CCBHourlyRate-(G8-CCBThreshold)*CCBThresholdModifier) ) )) -> 0 | L8: =MIN((J8-K8) * CCRRate, (CCRMax*H8)) -> 7613 | M8: =J8-(K8+L8) -> 8222
A9: caya-02 | B9: Caya | C9: Villette | D9: Caya | E9: Claude | F9: Lundqvist | G9: 147000 | H9: =COUNTIF(Children!$B$13:$B$128,A9) -> 1 | I9: =10*SUMIFS(Children!$K$13:$K$128,Children!$B$13:$B$128,Families!A9) -> 30 | J9: =SUMIFS(Children!$Q$13:$Q$128,Children!$B$13:$B$128,Families!A9) -> 14340 | K9: =MAX(0,IF(G9<CCBThreshold, IF(I9/H9<CCBMaxHours, I9*52*CCBHourlyRate, 50*52*CCBHourlyRate ), IF(I9/H9<50, I9*52*(CCBHourlyRate-(G9-CCBThreshold)*CCBThresholdModifier), 50*52*(CCBHourlyRate-(G9-CCBThreshold)*CCBThresholdModifier) ) )) -> 88.51596 | L9: =MIN((J9-K9) * CCRRate, (CCRMax*H9)) -> 7125.742 | M9: =J9-(K9+L9) -> 7125.742
A10: chien-03 | B10: Chien | C10: Hui | D10: Chien | E10: Kuan-Yin | F10: Burger | G10: 170713 | H10: =COUNTIF(Children!$B$13:$B$128,A10) -> 2 | I10: =10*SUMIFS(Children!$K$13:$K$128,Children!$B$13:$B$128,Families!A10) -> 80 | J10: =SUMIFS(Children!$Q$13:$Q$128,Children!$B$13:$B$128,Families!A10) -> 42115 | K10: =MAX(0,IF(G10<CCBThreshold, IF(I10/H10<CCBMaxHours, I10*52*CCBHourlyRate, 50*52*CCBHourlyRate ), IF(I10/H10<50, I10*52*(CCBHourlyRate-(G10-CCBThreshold)*CCBThresholdModifier), 50*52*(CCBHourlyRate-(G10-CCBThreshold)*CCBThresholdModifier) ) )) -> 0 | L10: =MIN((J10-K10) * CCRRate, (CCRMax*H10)) -> 15226 | M10: =J10-(K10+L10) -> 26889
A11: coburn-02 | B11: Coburn | C11: Hannah | D11: Coburn | E11: Cedric | F11: Coburn | G11: 165435 | H11: =COUNTIF(Children!$B$13:$B$128,A11) -> 2 | I11: =10*SUMIFS(Children!$K$13:$K$128,Children!$B$13:$B$128,Families!A11) -> 80 | J11: =SUMIFS(Children!$Q$13:$Q$128,Children!$B$13:$B$128,Families!A11) -> 47135 | K11: =MAX(0,IF(G11<CCBThreshold, IF(I11/H11<CCBMaxHours, I11*52*CCBHourlyRate, 50*52*CCBHourlyRate ), IF(I11/H11<50, I11*52*(CCBHourlyRate-(G11-CCBThreshold)*CCBThresholdModifier), 50*52*(CCBHourlyRate-(G11-CCBThreshold)*CCBThresholdModifier) ) )) -> 0 | L11: =MIN((J11-K11) * CCRRate, (CCRMax*H11)) -> 15226 | M11: =J11-(K11+L11) -> 31909
A12: course-01 | B12: Course | C12: Astolpho | D12: Course | E12: Clemence | F12: Course | G12: 118250 | H12: =COUNTIF(Children!$B$13:$B$128,A12) -> 1 | I12: =10*SUMIFS(Children!$K$13:$K$128,Children!$B$13:$B$128,Families!A12) -> 40 | J12: =SUMIFS(Children!$Q$13:$Q$128,Children!$B$13:$B$128,Families!A12) -> 17395 | K12: =MAX(0,IF(G12<CCBThreshold, IF(I12/H12<CCBMaxHours, I12*52*CCBHourlyRate, 50*52*CCBHourlyRate ), IF(I12/H12<50, I12*52*(CCBHourlyRate-(G12-CCBThreshold)*CCBThresholdModifier), 50*52*(CCBHourlyRate-(G12-CCBThreshold)*CCBThresholdModifier) ) )) -> 506.72128 | L12: =MIN((J12-K12) * CCRRate, (CCRMax*H12)) -> 7613 | M12: =J12-(K12+L12) -> 9275.2787
A13: crombie-03 | B13: Crombie | C13: Justin | D13: Crombie | E13: Janis | F13: Phillips | G13: 163683 | H13: =COUNTIF(Children!$B$13:$B$128,A13) -> 4 | I13: =10*SUMIFS(Children!$K$13:$K$128,Children!$B$13:$B$128,Families!A13) -> 200 | J13: =SUMIFS(Children!$Q$13:$Q$128,Children!$B$13:$B$128,Families!A13) -> 108350 | K13: =MAX(0,IF(G13<CCBThreshold, IF(I13/H13<CCBMaxHours, I13*52*CCBHourlyRate, 50*52*CCBHourlyRate ), IF(I13/H13<50, I13*52*(CCBHourlyRate-(G13-CCBThreshold)*CCBThresholdModifier), 50*52*(CCBHourlyRate-(G13-CCBThreshold)*CCBThresholdModifier) ) )) -> 0 | L13: =MIN((J13-K13) * CCRRate, (CCRMax*H13)) -> 30452 | M13: =J13-(K13+L13) -> 77898
A14: dastous-01 | B14: Dastous | C14: Fletcher | D14: Dastous | E14: Sabine | F14: Dastous | G14: 166400 | H14: =COUNTIF(Children!$B$13:$B$128,A14) -> 1 | I14: =10*SUMIFS(Children!$K$13:$K$128,Children!$B$13:$B$128,Families!A14) -> 50 | J14: =SUMIFS(Children!$Q$13:$Q$128,Children!$B$13:$B$128,Families!A14) -> 18695 | K14: =MAX(0,IF(G14<CCBThreshold, IF(I14/H14<CCBMaxHours, I14*52*CCBHourlyRate, 50*52*CCBHourlyRate ), IF(I14/H14<50, I14*52*(CCBHourlyRate-(G14-CCBThreshold)*CCBThresholdModifier), 50*52*(CCBHourlyRate-(G14-CCBThreshold)*CCBThresholdModifier) ) )) -> 0 | L14: =MIN((J14-K14) * CCRRate, (CCRMax*H14)) -> 7613 | M14: =J14-(K14+L14) -> 11082
A15: dorrington-01 | B15: Dorrington | C15: Jacob | D15: Dorrington | G15: 35533 | H15: =COUNTIF(Children!$B$13:$B$128,A15) -> 1 | I15: =10*SUMIFS(Children!$K$13:$K$128,Children!$B$13:$B$128,Families!A15) -> 10 | J15: =SUMIFS(Children!$Q$13:$Q$128,Children!$B$13:$B$128,Families!A15) -> 5070 | K15: =MAX(0,IF(G15<CCBThreshold, IF(I15/H15<CCBMaxHours, I15*52*CCBHourlyRate, 50*52*CCBHourlyRate ), IF(I15/H15<50, I15*52*(CCBHourlyRate-(G15-CCBThreshold)*CCBThresholdModifier), 50*52*(CCBHourlyRate-(G15-CCBThreshold)*CCBThresholdModifier) ) )) -> 373.88 | L15: =MIN((J15-K15) * CCRRate, (CCRMax*H15)) -> 2348.06 | M15: =J15-(K15+L15) -> 2348.06
A16: duggan-03 | B16: Duggan | C16: Jackson | D16: Duggan | E16: Marlene | F16: Duggan | G16: 172321 | H16: =COUNTIF(Children!$B$13:$B$128,A16) -> 4 | I16: =10*SUMIFS(Children!$K$13:$K$128,Children!$B$13:$B$128,Families!A16) -> 120 | J16: =SUMIFS(Children!$Q$13:$Q$128,Children!$B$13:$B$128,Families!A16) -> 68740 | K16: =MAX(0,IF(G16<CCBThreshold, IF(I16/H16<CCBMaxHours, I16*52*CCBHourlyRate, 50*52*CCBHourlyRate ), IF(I16/H16<50, I16*52*(CCBHourlyRate-(G16-CCBThreshold)*CCBThresholdModifier), 50*52*(CCBHourlyRate-(G16-CCBThreshold)*CCBThresholdModifier) ) )) -> 0 | L16: =MIN((J16-K16) * CCRRate, (CCRMax*H16)) -> 30452 | M16: =J16-(K16+L16) -> 38288
A17: dumaresq-03 | B17: Dumaresq | C17: Molly | D17: Dumaresq | F17: Erickson | G17: 137112 | H17: =COUNTIF(Children!$B$13:$B$128,A17) -> 1 | I17: =10*SUMIFS(Children!$K$13:$K$128,Children!$B$13:$B$128,Families!A17) -> 40 | J17: =SUMIFS(Children!$Q$13:$Q$128,Children!$B$13:$B$128,Families!A17) -> 15355 | K17: =MAX(0,IF(G17<CCBThreshold, IF(I17/H17<CCBMaxHours, I17*52*CCBHourlyRate, 50*52*CCBHourlyRate ), IF(I17/H17<50, I17*52*(CCBHourlyRate-(G17-CCBThreshold)*CCBThresholdModifier), 50*52*(CCBHourlyRate-(G17-CCBThreshold)*CCBThresholdModifier) ) )) -> 251.70704 | L17: =MIN((J17-K17) * CCRRate, (CCRMax*H17)) -> 7551.6465 | M17: =J17-(K17+L17) -> 7551.6465
A18: duranseau-01 | B18: Duranseau | C18: Fleurette | D18: Duranseau | E18: Arienne | F18: Dreher | G18: 142117 | H18: =COUNTIF(Children!$B$13:$B$128,A18) -> 1 | I18: =10*SUMIFS(Children!$K$13:$K$128,Children!$B$13:$B$128,Families!A18) -> 30 | J18: =SUMIFS(Children!$Q$13:$Q$128,Children!$B$13:$B$128,Families!A18) -> 12795 | K18: =MAX(0,IF(G18<CCBThreshold, IF(I18/H18<CCBMaxHours, I18*52*CCBHourlyRate, 50*52*CCBHourlyRate ), IF(I18/H18<50, I18*52*(CCBHourlyRate-(G18-CCBThreshold)*CCBThresholdModifier), 50*52*(CCBHourlyRate-(G18-CCBThreshold)*CCBThresholdModifier) ) )) -> 138.02958 | L18: =MIN((J18-K18) * CCRRate, (CCRMax*H18)) -> 6328.4852 | M18: =J18-(K18+L18) -> 6328.4852
A19: eatock-01 | B19: Eatock | C19: Charlotte | D19: Eatock | E19: Robert | F19: Eatock | G19: 76982 | H19: =COUNTIF(Children!$B$13:$B$128,A19) -> 2 | I19: =10*SUMIFS(Children!$K$13:$K$128,Children!$B$13:$B$128,Families!A19) -> 60 | J19: =SUMIFS(Children!$Q$13:$Q$128,Children!$B$13:$B$128,Families!A19) -> 23375 | K19: =MAX(0,IF(G19<CCBThreshold, IF(I19/H19<CCBMaxHours, I19*52*CCBHourlyRate, 50*52*CCBHourlyRate ), IF(I19/H19<50, I19*52*(CCBHourlyRate-(G19-CCBThreshold)*CCBThresholdModifier), 50*52*(CCBHourlyRate-(G19-CCBThreshold)*CCBThresholdModifier) ) )) -> 1596.997 | L19: =MIN((J19-K19) * CCRRate, (CCRMax*H19)) -> 10889.002 | M19: =J19-(K19+L19) -> 10889.002
A20: edgerton-01 | B20: Edgerton | C20: Kiara | D20: Edgerton | G20: 69888 | H20: =COUNTIF(Children!$B$13:$B$128,A20) -> 1 | I20: =10*SUMIFS(Children!$K$13:$K$128,Children!$B$13:$B$128,Families!A20) -> 10 | J20: =SUMIFS(Children!$Q$13:$Q$128,Children!$B$13:$B$128,Families!A20) -> 4310 | K20: =MAX(0,IF(G20<CCBThreshold, IF(I20/H20<CCBMaxHours, I20*52*CCBHourlyRate, 50*52*CCBHourlyRate ), IF(I20/H20<50, I20*52*(CCBHourlyRate-(G20-CCBThreshold)*CCBThresholdModifier), 50*52*(CCBHourlyRate-(G20-CCBThreshold)*CCBThresholdModifier) ) )) -> 290.14388 | L20: =MIN((J20-K20) * CCRRate, (CCRMax*H20)) -> 2009.9281 | M20: =J20-(K20+L20) -> 2009.9281
A21: fantl-02 | B21: Fantl | C21: Natasha | D21: Fantl | G21: 50642 | H21: =COUNTIF(Children!$B$13:$B$128,A21) -> 2 | I21: =10*SUMIFS(Children!$K$13:$K$128,Children!$B$13:$B$128,Families!A21) -> 60 | J21: =SUMIFS(Children!$Q$13:$Q$128,Children!$B$13:$B$128,Families!A21) -> 38000 | K21: =MAX(0,IF(G21<CCBThreshold, IF(I21/H21<CCBMaxHours, I21*52*CCBHourlyRate, 50*52*CCBHourlyRate ), IF(I21/H21<50, I21*52*(CCBHourlyRate-(G21-CCBThreshold)*CCBThresholdModifier), 50*52*(CCBHourlyRate-(G21-CCBThreshold)*CCBThresholdModifier) ) )) -> 2131.1722 | L21: =MIN((J21-K21) * CCRRate, (CCRMax*H21)) -> 15226 | M21: =J21-(K21+L21) -> 20642.828
A22: farquhar-03 | B22: Farquhar | C22: Margaret | D22: Farquhar | E22: Billy | F22: Farquhar | G22: 101239 | H22: =COUNTIF(Children!$B$13:$B$128,A22) -> 2 | I22: =10*SUMIFS(Children!$K$13:$K$128,Children!$B$13:$B$128,Families!A22) -> 60 | J22: =SUMIFS(Children!$Q$13:$Q$128,Children!$B$13:$B$128,Families!A22) -> 26960 | K22: =MAX(0,IF(G22<CCBThreshold, IF(I22/H22<CCBMaxHours, I22*52*CCBHourlyRate, 50*52*CCBHourlyRate ), IF(I22/H22<50, I22*52*(CCBHourlyRate-(G22-CCBThreshold)*CCBThresholdModifier), 50*52*(CCBHourlyRate-(G22-CCBThreshold)*CCBThresholdModifier) ) )) -> 1105.065 | L22: =MIN((J22-K22) * CCRRate, (CCRMax*H22)) -> 12927.468 | M22: =J22-(K22+L22) -> 12927.467
A23: fichter-02 | B23: Fichter | C23: Billy | D23: Fichter | E23: Peggy | F23: Fichter | G23: 164844 | H23: =COUNTIF(Children!$B$13:$B$128,A23) -> 3 | I23: =10*SUMIFS(Children!$K$13:$K$128,Children!$B$13:$B$128,Families!A23) -> 120 | J23: =SUMIFS(Children!$Q$13:$Q$128,Children!$B$13:$B$128,Families!A23) -> 63385 | K23: =MAX(0,IF(G23<CCBThreshold, IF(I23/H23<CCBMaxHours, I23*52*CCBHourlyRate, 50*52*CCBHourlyRate ), IF(I23/H23<50, I23*52*(CCBHourlyRate-(G23-CCBThreshold)*CCBThresholdModifier), 50*52*(CCBHourlyRate-(G23-CCBThreshold)*CCBThresholdModifier) ) )) -> 0 | L23: =MIN((J23-K23) * CCRRate, (CCRMax*H23)) -> 22839 | M23: =J23-(K23+L23) -> 40546
A24: gallegos-03 | B24: Gallegos | C24: Bertha | D24: Gallegos | E24: Saville | F24: Gallegos | G24: 180224 | H24: =COUNTIF(Children!$B$13:$B$128,A24) -> 2 | I24: =10*SUMIFS(Children!$K$13:$K$128,Children!$B$13:$B$128,Families!A24) -> 80 | J24: =SUMIFS(Children!$Q$13:$Q$128,Children!$B$13:$B$128,Families!A24) -> 34980 | K24: =MAX(0,IF(G24<CCBThreshold, IF(I24/H24<CCBMaxHours, I24*52*CCBHourlyRate, 50*52*CCBHourlyRate ), IF(I24/H24<50, I24*52*(CCBHourlyRate-(G24-CCBThreshold)*CCBThresholdModifier), 50*52*(CCBHourlyRate-(G24-CCBThreshold)*CCBThresholdModifier) ) )) -> 0 | L24: =MIN((J24-K24) * CCRRate, (CCRMax*H24)) -> 15226 | M24: =J24-(K24+L24) -> 19754
A25: gallop-03 | B25: Gallop | C25: Annabelle | D25: Gallop | G25: 60884 | H25: =COUNTIF(Children!$B$13:$B$128,A25) -> 2 | I25: =10*SUMIFS(Children!$K$13:$K$128,Children!$B$13:$B$128,Families!A25) -> 80 | J25: =SUMIFS(Children!$Q$13:$Q$128,Children!$B$13:$B$128,Families!A25) -> 37945 | K25: =MAX(0,IF(G25<CCBThreshold, IF(I25/H25<CCBMaxHours, I25*52*CCBHourlyRate, 50*52*CCBHourlyRate ), IF(I25/H25<50, I25*52*(CCBHourlyRate-(G25-CCBThreshold)*CCBThresholdModifier), 50*52*(CCBHourlyRate-(G25-CCBThreshold)*CCBThresholdModifier) ) )) -> 2564.6192 | L25: =MIN((J25-K25) * CCRRate, (CCRMax*H25)) -> 15226 | M25: =J25-(K25+L25) -> 20154.381
A26: garreau-01 | B26: Garreau | C26: Rene | D26: Garreau | E26: Olympia | F26: Garreau | G26: 105305 | H26: =COUNTIF(Children!$B$13:$B$128,A26) -> 1 | I26: =10*SUMIFS(Children!$K$13:$K$128,Children!$B$13:$B$128,Families!A26) -> 30 | J26: =SUMIFS(Children!$Q$13:$Q$128,Children!$B$13:$B$128,Families!A26) -> 14270 | K26: =MAX(0,IF(G26<CCBThreshold, IF(I26/H26<CCBMaxHours, I26*52*CCBHourlyRate, 50*52*CCBHourlyRate ), IF(I26/H26<50, I26*52*(CCBHourlyRate-(G26-CCBThreshold)*CCBThresholdModifier), 50*52*(CCBHourlyRate-(G26-CCBThreshold)*CCBThresholdModifier) ) )) -> 511.30326 | L26: =MIN((J26-K26) * CCRRate, (CCRMax*H26)) -> 6879.3484 | M26: =J26-(K26+L26) -> 6879.3484
A27: hertzog-03 | B27: Hertzog | C27: Michael | D27: Hertzog | E27: Lea | F27: Hertzog | G27: 107083 | H27: =COUNTIF(Children!$B$13:$B$128,A27) -> 1 | I27: =10*SUMIFS(Children!$K$13:$K$128,Children!$B$13:$B$128,Families!A27) -> 30 | J27: =SUMIFS(Children!$Q$13:$Q$128,Children!$B$13:$B$128,Families!A27) -> 16720 | K27: =MAX(0,IF(G27<CCBThreshold, IF(I27/H27<CCBMaxHours, I27*52*CCBHourlyRate, 50*52*CCBHourlyRate ), IF(I27/H27<50, I27*52*(CCBHourlyRate-(G27-CCBThreshold)*CCBThresholdModifier), 50*52*(CCBHourlyRate-(G27-CCBThreshold)*CCBThresholdModifier) ) )) -> 493.27434 | L27: =MIN((J27-K27) * CCRRate, (CCRMax*H27)) -> 7613 | M27: =J27-(K27+L27) -> 8613.7257
A28: isom-01 | B28: Isom | C28: Natalie | D28: Isom | G28: 63252 | H28: =COUNTIF(Children!$B$13:$B$128,A28) -> 1 | I28: =10*SUMIFS(Children!$K$13:$K$128,Children!$B$13:$B$128,Families!A28) -> 50 | J28: =SUMIFS(Children!$Q$13:$Q$128,Children!$B$13:$B$128,Families!A28) -> 19305 | K28: =MAX(0,IF(G28<CCBThreshold, IF(I28/H28<CCBMaxHours, I28*52*CCBHourlyRate, 50*52*CCBHourlyRate ), IF(I28/H28<50, I28*52*(CCBHourlyRate-(G28-CCBThreshold)*CCBThresholdModifier), 50*52*(CCBHourlyRate-(G28-CCBThreshold)*CCBThresholdModifier) ) )) -> 1562.8678 | L28: =MIN((J28-K28) * CCRRate, (CCRMax*H28)) -> 7613 | M28: =J28-(K28+L28) -> 10129.132
A29: jackey-02 | B29: Jackey | C29: Chelsea | D29: Jackey | G29: 48475 | H29: =COUNTIF(Children!$B$13:$B$128,A29) -> 2 | I29: =10*SUMIFS(Children!$K$13:$K$128,Children!$B$13:$B$128,Families!A29) -> 100 | J29: =SUMIFS(Children!$Q$13:$Q$128,Children!$B$13:$B$128,Families!A29) -> 48165 | K29: =MAX(0,IF(G29<CCBThreshold, IF(I29/H29<CCBMaxHours, I29*52*CCBHourlyRate, 50*52*CCBHourlyRate ), IF(I29/H29<50, I29*52*(CCBHourlyRate-(G29-CCBThreshold)*CCBThresholdModifier), 50*52*(CCBHourlyRate-(G29-CCBThreshold)*CCBThresholdModifier) ) )) -> 1812.5991 | L29: =MIN((J29-K29) * CCRRate, (CCRMax*H29)) -> 15226 | M29: =J29-(K29+L29) -> 31126.401
A30: johann-01 | B30: Johann | C30: Dominic | D30: Johann | E30: Laura | F30: Edwards | G30: 148644 | H30: =COUNTIF(Children!$B$13:$B$128,A30) -> 2 | I30: =10*SUMIFS(Children!$K$13:$K$128,Children!$B$13:$B$128,Families!A30) -> 100 | J30: =SUMIFS(Children!$Q$13:$Q$128,Children!$B$13:$B$128,Families!A30) -> 43460 | K30: =MAX(0,IF(G30<CCBThreshold, IF(I30/H30<CCBMaxHours, I30*52*CCBHourlyRate, 50*52*CCBHourlyRate ), IF(I30/H30<50, I30*52*(CCBHourlyRate-(G30-CCBThreshold)*CCBThresholdModifier), 50*52*(CCBHourlyRate-(G30-CCBThreshold)*CCBThresholdModifier) ) )) -> 119.743 | L30: =MIN((J30-K30) * CCRRate, (CCRMax*H30)) -> 15226 | M30: =J30-(K30+L30) -> 28114.257
A31: kamuta-01 | B31: Kamuta | C31: Yuugou | D31: Kamuta | E31: Hatomi | F31: Kamuta | G31: 200555 | H31: =COUNTIF(Children!$B$13:$B$128,A31) -> 4 | I31: =10*SUMIFS(Children!$K$13:$K$128,Children!$B$13:$B$128,Families!A31) -> 160 | J31: =SUMIFS(Children!$Q$13:$Q$128,Children!$B$13:$B$128,Families!A31) -> 77430 | K31: =MAX(0,IF(G31<CCBThreshold, IF(I31/H31<CCBMaxHours, I31*52*CCBHourlyRate, 50*52*CCBHourlyRate ), IF(I31/H31<50, I31*52*(CCBHourlyRate-(G31-CCBThreshold)*CCBThresholdModifier), 50*52*(CCBHourlyRate-(G31-CCBThreshold)*CCBThresholdModifier) ) )) -> 0 | L31: =MIN((J31-K31) * CCRRate, (CCRMax*H31)) -> 30452 | M31: =J31-(K31+L31) -> 46978
A32: kasai-03 | B32: Kasai | C32: Kazumu | D32: Kasai | E32: Itsuyo | F32: Kasai | G32: 99004 | H32: =COUNTIF(Children!$B$13:$B$128,A32) -> 1 | I32: =10*SUMIFS(Children!$K$13:$K$128,Children!$B$13:$B$128,Families!A32) -> 20 | J32: =SUMIFS(Children!$Q$13:$Q$128,Children!$B$13:$B$128,Families!A32) -> 8775 | K32: =MAX(0,IF(G32<CCBThreshold, IF(I32/H32<CCBMaxHours, I32*52*CCBHourlyRate, 50*52*CCBHourlyRate ), IF(I32/H32<50, I32*52*(CCBHourlyRate-(G32-CCBThreshold)*CCBThresholdModifier), 50*52*(CCBHourlyRate-(G32-CCBThreshold)*CCBThresholdModifier) ) )) -> 383.4636 | L32: =MIN((J32-K32) * CCRRate, (CCRMax*H32)) -> 4195.7682 | M32: =J32-(K32+L32) -> 4195.7682
A33: kouno-01 | B33: Kouno | C33: Genya | D33: Kouno | E33: Akari | F33: Kouno | G33: 146375 | H33: =COUNTIF(Children!$B$13:$B$128,A33) -> 1 | I33: =10*SUMIFS(Children!$K$13:$K$128,Children!$B$13:$B$128,Families!A33) -> 40 | J33: =SUMIFS(Children!$Q$13:$Q$128,Children!$B$13:$B$128,Families!A33) -> 18170 | K33: =MAX(0,IF(G33<CCBThreshold, IF(I33/H33<CCBMaxHours, I33*52*CCBHourlyRate, 50*52*CCBHourlyRate ), IF(I33/H33<50, I33*52*(CCBHourlyRate-(G33-CCBThreshold)*CCBThresholdModifier), 50*52*(CCBHourlyRate-(G33-CCBThreshold)*CCBThresholdModifier) ) )) -> 126.47128 | L33: =MIN((J33-K33) * CCRRate, (CCRMax*H33)) -> 7613 | M33: =J33-(K33+L33) -> 10430.529
A34: kraegen-01 | B34: Kraegen | C34: Taylah | D34: Kraegen | G34: 55875 | H34: =COUNTIF(Children!$B$13:$B$128,A34) -> 1 | I34: =10*SUMIFS(Children!$K$13:$K$128,Children!$B$13:$B$128,Families!A34) -> 30 | J34: =SUMIFS(Children!$Q$13:$Q$128,Children!$B$13:$B$128,Families!A34) -> 14205 | K34: =MAX(0,IF(G34<CCBThreshold, IF(I34/H34<CCBMaxHours, I34*52*CCBHourlyRate, 50*52*CCBHourlyRate ), IF(I34/H34<50, I34*52*(CCBHourlyRate-(G34-CCBThreshold)*CCBThresholdModifier), 50*52*(CCBHourlyRate-(G34-CCBThreshold)*CCBThresholdModifier) ) )) -> 1012.5235 | L34: =MIN((J34-K34) * CCRRate, (CCRMax*H34)) -> 6596.2383 | M34: =J34-(K34+L34) -> 6596.2383
A35: langlais-02 | B35: Langlais | C35: Danielle | D35: Langlais | E35: Voleta | F35: Ponce | G35: 117501 | H35: =COUNTIF(Children!$B$13:$B$128,A35) -> 2 | I35: =10*SUMIFS(Children!$K$13:$K$128,Children!$B$13:$B$128,Families!A35) -> 20 | J35: =SUMIFS(Children!$Q$13:$Q$128,Children!$B$13:$B$128,Families!A35) -> 9655 | K35: =MAX(0,IF(G35<CCBThreshold, IF(I35/H35<CCBMaxHours, I35*52*CCBHourlyRate, 50*52*CCBHourlyRate ), IF(I35/H35<50, I35*52*(CCBHourlyRate-(G35-CCBThreshold)*CCBThresholdModifier), 50*52*(CCBHourlyRate-(G35-CCBThreshold)*CCBThresholdModifier) ) )) -> 258.42388 | L35: =MIN((J35-K35) * CCRRate, (CCRMax*H35)) -> 4698.2881 | M35: =J35-(K35+L35) -> 4698.2881
A36: leveille-02 | B36: Leveille | C36: Maurice | D36: Leveille | E36: Germaine | F36: Leveille | G36: 137895 | H36: =COUNTIF(Children!$B$13:$B$128,A36) -> 1 | I36: =10*SUMIFS(Children!$K$13:$K$128,Children!$B$13:$B$128,Families!A36) -> 50 | J36: =SUMIFS(Children!$Q$13:$Q$128,Children!$B$13:$B$128,Families!A36) -> 23760 | K36: =MAX(0,IF(G36<CCBThreshold, IF(I36/H36<CCBMaxHours, I36*52*CCBHourlyRate, 50*52*CCBHourlyRate ), IF(I36/H36<50, I36*52*(CCBHourlyRate-(G36-CCBThreshold)*CCBThresholdModifier), 50*52*(CCBHourlyRate-(G36-CCBThreshold)*CCBThresholdModifier) ) )) -> 301.4011 | L36: =MIN((J36-K36) * CCRRate, (CCRMax*H36)) -> 7613 | M36: =J36-(K36+L36) -> 15845.599
A37: marian-03 | B37: Marian | C37: Jai | D37: Marian | E37: Jonas | F37: Lundgren | G37: 129299 | H37: =COUNTIF(Children!$B$13:$B$128,A37) -> 1 | I37: =10*SUMIFS(Children!$K$13:$K$128,Children!$B$13:$B$128,Families!A37) -> 20 | J37: =SUMIFS(Children!$Q$13:$Q$128,Children!$B$13:$B$128,Families!A37) -> 13330 | K37: =MAX(0,IF(G37<CCBThreshold, IF(I37/H37<CCBMaxHours, I37*52*CCBHourlyRate, 50*52*CCBHourlyRate ), IF(I37/H37<50, I37*52*(CCBHourlyRate-(G37-CCBThreshold)*CCBThresholdModifier), 50*52*(CCBHourlyRate-(G37-CCBThreshold)*CCBThresholdModifier) ) )) -> 178.6694 | L37: =MIN((J37-K37) * CCRRate, (CCRMax*H37)) -> 6575.6653 | M37: =J37-(K37+L37) -> 6575.6653
A38: mcguirk-03 | B38: McGuirk | C38: Keira | D38: McGuirk | G38: 43492 | H38: =COUNTIF(Children!$B$13:$B$128,A38) -> 2 | I38: =10*SUMIFS(Children!$K$13:$K$128,Children!$B$13:$B$128,Families!A38) -> 100 | J38: =SUMIFS(Children!$Q$13:$Q$128,Children!$B$13:$B$128,Families!A38) -> 50005 | K38: =MAX(0,IF(G38<CCBThreshold, IF(I38/H38<CCBMaxHours, I38*52*CCBHourlyRate, 50*52*CCBHourlyRate ), IF(I38/H38<50, I38*52*(CCBHourlyRate-(G38-CCBThreshold)*CCBThresholdModifier), 50*52*(CCBHourlyRate-(G38-CCBThreshold)*CCBThresholdModifier) ) )) -> 1869.4 | L38: =MIN((J38-K38) * CCRRate, (CCRMax*H38)) -> 15226 | M38: =J38-(K38+L38) -> 32909.6
A39: mckean-03 | B39: McKean | C39: Julian | D39: McKean | G39: 39345 | H39: =COUNTIF(Children!$B$13:$B$128,A39) -> 1 | I39: =10*SUMIFS(Children!$K$13:$K$128,Children!$B$13:$B$128,Families!A39) -> 40 | J39: =SUMIFS(Children!$Q$13:$Q$128,Children!$B$13:$B$128,Families!A39) -> 20130 | K39: =MAX(0,IF(G39<CCBThreshold, IF(I39/H39<CCBMaxHours, I39*52*CCBHourlyRate, 50*52*CCBHourlyRate ), IF(I39/H39<50, I39*52*(CCBHourlyRate-(G39-CCBThreshold)*CCBThresholdModifier), 50*52*(CCBHourlyRate-(G39-CCBThreshold)*CCBThresholdModifier) ) )) -> 1495.52 | L39: =MIN((J39-K39) * CCRRate, (CCRMax*H39)) -> 7613 | M39: =J39-(K39+L39) -> 11021.48
A40: moore-01 | B40: Moore | C40: Rey | D40: Moore | E40: George | F40: Chu | G40: 131195 | H40: =COUNTIF(Children!$B$13:$B$128,A40) -> 2 | I40: =10*SUMIFS(Children!$K$13:$K$128,Children!$B$13:$B$128,Families!A40) -> 100 | J40: =SUMIFS(Children!$Q$13:$Q$128,Children!$B$13:$B$128,Families!A40) -> 38060 | K40: =MAX(0,IF(G40<CCBThreshold, IF(I40/H40<CCBMaxHours, I40*52*CCBHourlyRate, 50*52*CCBHourlyRate ), IF(I40/H40<50, I40*52*(CCBHourlyRate-(G40-CCBThreshold)*CCBThresholdModifier), 50*52*(CCBHourlyRate-(G40-CCBThreshold)*CCBThresholdModifier) ) )) -> 414.6311 | L40: =MIN((J40-K40) * CCRRate, (CCRMax*H40)) -> 15226 | M40: =J40-(K40+L40) -> 22419.369
A41: mowery-02 | B41: Mowery | C41: Adam | D41: Mowery | E41: Laura | F41: Foerster | G41: 142170 | H41: =COUNTIF(Children!$B$13:$B$128,A41) -> 1 | I41: =10*SUMIFS(Children!$K$13:$K$128,Children!$B$13:$B$128,Families!A41) -> 40 | J41: =SUMIFS(Children!$Q$13:$Q$128,Children!$B$13:$B$128,Families!A41) -> 19135 | K41: =MAX(0,IF(G41<CCBThreshold, IF(I41/H41<CCBMaxHours, I41*52*CCBHourlyRate, 50*52*CCBHourlyRate ), IF(I41/H41<50, I41*52*(CCBHourlyRate-(G41-CCBThreshold)*CCBThresholdModifier), 50*52*(CCBHourlyRate-(G41-CCBThreshold)*CCBThresholdModifier) ) )) -> 183.32288 | L41: =MIN((J41-K41) * CCRRate, (CCRMax*H41)) -> 7613 | M41: =J41-(K41+L41) -> 11338.677
A42: nixon-03 | B42: Nixon | C42: Bernie | D42: Nixon | G42: 47928 | H42: =COUNTIF(Children!$B$13:$B$128,A42) -> 1 | I42: =10*SUMIFS(Children!$K$13:$K$128,Children!$B$13:$B$128,Families!A42) -> 50 | J42: =SUMIFS(Children!$Q$13:$Q$128,Children!$B$13:$B$128,Families!A42) -> 18450 | K42: =MAX(0,IF(G42<CCBThreshold, IF(I42/H42<CCBMaxHours, I42*52*CCBHourlyRate, 50*52*CCBHourlyRate ), IF(I42/H42<50, I42*52*(CCBHourlyRate-(G42-CCBThreshold)*CCBThresholdModifier), 50*52*(CCBHourlyRate-(G42-CCBThreshold)*CCBThresholdModifier) ) )) -> 1821.8434 | L42: =MIN((J42-K42) * CCRRate, (CCRMax*H42)) -> 7613 | M42: =J42-(K42+L42) -> 9015.1566
A43: obrien-01 | B43: Obrien | C43: Pat | D43: Obrien | E43: Sandra | F43: Obrien | G43: 178989 | H43: =COUNTIF(Children!$B$13:$B$128,A43) -> 2 | I43: =10*SUMIFS(Children!$K$13:$K$128,Children!$B$13:$B$128,Families!A43) -> 40 | J43: =SUMIFS(Children!$Q$13:$Q$128,Children!$B$13:$B$128,Families!A43) -> 19280 | K43: =MAX(0,IF(G43<CCBThreshold, IF(I43/H43<CCBMaxHours, I43*52*CCBHourlyRate, 50*52*CCBHourlyRate ), IF(I43/H43<50, I43*52*(CCBHourlyRate-(G43-CCBThreshold)*CCBThresholdModifier), 50*52*(CCBHourlyRate-(G43-CCBThreshold)*CCBThresholdModifier) ) )) -> 0 | L43: =MIN((J43-K43) * CCRRate, (CCRMax*H43)) -> 9640 | M43: =J43-(K43+L43) -> 9640
A44: osburne-03 | B44: Osburne | C44: Nicholas | D44: Osburne | E44: Jennifer | F44: Osburne | G44: 180230 | H44: =COUNTIF(Children!$B$13:$B$128,A44) -> 3 | I44: =10*SUMIFS(Children!$K$13:$K$128,Children!$B$13:$B$128,Families!A44) -> 90 | J44: =SUMIFS(Children!$Q$13:$Q$128,Children!$B$13:$B$128,Families!A44) -> 36690 | K44: =MAX(0,IF(G44<CCBThreshold, IF(I44/H44<CCBMaxHours, I44*52*CCBHourlyRate, 50*52*CCBHourlyRate ), IF(I44/H44<50, I44*52*(CCBHourlyRate-(G44-CCBThreshold)*CCBThresholdModifier), 50*52*(CCBHourlyRate-(G44-CCBThreshold)*CCBThresholdModifier) ) )) -> 0 | L44: =MIN((J44-K44) * CCRRate, (CCRMax*H44)) -> 18345 | M44: =J44-(K44+L44) -> 18345
A45: pelensky-02 | B45: Pelensky | C45: Lily | D45: Pelensky | E45: Anthony | F45: Pelensky | G45: 106541 | H45: =COUNTIF(Children!$B$13:$B$128,A45) -> 1 | I45: =10*SUMIFS(Children!$K$13:$K$128,Children!$B$13:$B$128,Families!A45) -> 20 | J45: =SUMIFS(Children!$Q$13:$Q$128,Children!$B$13:$B$128,Families!A45) -> 8650 | K45: =MAX(0,IF(G45<CCBThreshold, IF(I45/H45<CCBMaxHours, I45*52*CCBHourlyRate, 50*52*CCBHourlyRate ), IF(I45/H45<50, I45*52*(CCBHourlyRate-(G45-CCBThreshold)*CCBThresholdModifier), 50*52*(CCBHourlyRate-(G45-CCBThreshold)*CCBThresholdModifier) ) )) -> 332.51348 | L45: =MIN((J45-K45) * CCRRate, (CCRMax*H45)) -> 4158.7433 | M45: =J45-(K45+L45) -> 4158.7433
A46: pelsaert-03 | B46: Pelsaert | C46: Rachel | D46: Pelsaert | E46: Adam | F46: Herrmann | G46: 170206 | H46: =COUNTIF(Children!$B$13:$B$128,A46) -> 3 | I46: =10*SUMIFS(Children!$K$13:$K$128,Children!$B$13:$B$128,Families!A46) -> 90 | J46: =SUMIFS(Children!$Q$13:$Q$128,Children!$B$13:$B$128,Families!A46) -> 48360 | K46: =MAX(0,IF(G46<CCBThreshold, IF(I46/H46<CCBMaxHours, I46*52*CCBHourlyRate, 50*52*CCBHourlyRate ), IF(I46/H46<50, I46*52*(CCBHourlyRate-(G46-CCBThreshold)*CCBThresholdModifier), 50*52*(CCBHourlyRate-(G46-CCBThreshold)*CCBThresholdModifier) ) )) -> 0 | L46: =MIN((J46-K46) * CCRRate, (CCRMax*H46)) -> 22839 | M46: =J46-(K46+L46) -> 25521
A47: penfold-02 | B47: Penfold | C47: Harrison | D47: Penfold | G47: 72606 | H47: =COUNTIF(Children!$B$13:$B$128,A47) -> 1 | I47: =10*SUMIFS(Children!$K$13:$K$128,Children!$B$13:$B$128,Families!A47) -> 30 | J47: =SUMIFS(Children!$Q$13:$Q$128,Children!$B$13:$B$128,Families!A47) -> 8230 | K47: =MAX(0,IF(G47<CCBThreshold, IF(I47/H47<CCBMaxHours, I47*52*CCBHourlyRate, 50*52*CCBHourlyRate ), IF(I47/H47<50, I47*52*(CCBHourlyRate-(G47-CCBThreshold)*CCBThresholdModifier), 50*52*(CCBHourlyRate-(G47-CCBThreshold)*CCBThresholdModifier) ) )) -> 842.87112 | L47: =MIN((J47-K47) * CCRRate, (CCRMax*H47)) -> 3693.5644 | M47: =J47-(K47+L47) -> 3693.5644
A48: quynh-03 | B48: Quynh | C48: Kim | D48: Quynh | E48: Chu | F48: Quynh | G48: 160219 | H48: =COUNTIF(Children!$B$13:$B$128,A48) -> 1 | I48: =10*SUMIFS(Children!$K$13:$K$128,Children!$B$13:$B$128,Families!A48) -> 20 | J48: =SUMIFS(Children!$Q$13:$Q$128,Children!$B$13:$B$128,Families!A48) -> 9165 | K48: =MAX(0,IF(G48<CCBThreshold, IF(I48/H48<CCBMaxHours, I48*52*CCBHourlyRate, 50*52*CCBHourlyRate ), IF(I48/H48<50, I48*52*(CCBHourlyRate-(G48-CCBThreshold)*CCBThresholdModifier), 50*52*(CCBHourlyRate-(G48-CCBThreshold)*CCBThresholdModifier) ) )) -> 0 | L48: =MIN((J48-K48) * CCRRate, (CCRMax*H48)) -> 4582.5 | M48: =J48-(K48+L48) -> 4582.5
A49: racine-03 | B49: Racine | C49: Aceline | D49: Racine | E49: Ogier | F49: Schmitt | G49: 167942 | H49: =COUNTIF(Children!$B$13:$B$128,A49) -> 1 | I49: =10*SUMIFS(Children!$K$13:$K$128,Children!$B$13:$B$128,Families!A49) -> 20 | J49: =SUMIFS(Children!$Q$13:$Q$128,Children!$B$13:$B$128,Families!A49) -> 8365 | K49: =MAX(0,IF(G49<CCBThreshold, IF(I49/H49<CCBMaxHours, I49*52*CCBHourlyRate, 50*52*CCBHourlyRate ), IF(I49/H49<50, I49*52*(CCBHourlyRate-(G49-CCBThreshold)*CCBThresholdModifier), 50*52*(CCBHourlyRate-(G49-CCBThreshold)*CCBThresholdModifier) ) )) -> 0 | L49: =MIN((J49-K49) * CCRRate, (CCRMax*H49)) -> 4182.5 | M49: =J49-(K49+L49) -> 4182.5
A50: rawson-02 | B50: Rawson | C50: Adam | D50: Rawson | E50: Janet | F50: Bainton | G50: 147217 | H50: =COUNTIF(Children!$B$13:$B$128,A50) -> 1 | I50: =10*SUMIFS(Children!$K$13:$K$128,Children!$B$13:$B$128,Families!A50) -> 20 | J50: =SUMIFS(Children!$Q$13:$Q$128,Children!$B$13:$B$128,Families!A50) -> 8205 | K50: =MAX(0,IF(G50<CCBThreshold, IF(I50/H50<CCBMaxHours, I50*52*CCBHourlyRate, 50*52*CCBHourlyRate ), IF(I50/H50<50, I50*52*(CCBHourlyRate-(G50-CCBThreshold)*CCBThresholdModifier), 50*52*(CCBHourlyRate-(G50-CCBThreshold)*CCBThresholdModifier) ) )) -> 57.54372 | L50: =MIN((J50-K50) * CCRRate, (CCRMax*H50)) -> 4073.7281 | M50: =J50-(K50+L50) -> 4073.7281
A51: revell-02 | B51: Revell | C51: George | D51: Revell | G51: 66987 | H51: =COUNTIF(Children!$B$13:$B$128,A51) -> 2 | I51: =10*SUMIFS(Children!$K$13:$K$128,Children!$B$13:$B$128,Families!A51) -> 60 | J51: =SUMIFS(Children!$Q$13:$Q$128,Children!$B$13:$B$128,Families!A51) -> 30965 | K51: =MAX(0,IF(G51<CCBThreshold, IF(I51/H51<CCBMaxHours, I51*52*CCBHourlyRate, 50*52*CCBHourlyRate ), IF(I51/H51<50, I51*52*(CCBHourlyRate-(G51-CCBThreshold)*CCBThresholdModifier), 50*52*(CCBHourlyRate-(G51-CCBThreshold)*CCBThresholdModifier) ) )) -> 1799.6956 | L51: =MIN((J51-K51) * CCRRate, (CCRMax*H51)) -> 14582.652 | M51: =J51-(K51+L51) -> 14582.652
A52: robinson-03 | B52: Robinson | C52: Kristin | D52: Robinson | E52: Kent | F52: Robinson | G52: 161645 | H52: =COUNTIF(Children!$B$13:$B$128,A52) -> 1 | I52: =10*SUMIFS(Children!$K$13:$K$128,Children!$B$13:$B$128,Families!A52) -> 30 | J52: =SUMIFS(Children!$Q$13:$Q$128,Children!$B$13:$B$128,Families!A52) -> 13515 | K52: =MAX(0,IF(G52<CCBThreshold, IF(I52/H52<CCBMaxHours, I52*52*CCBHourlyRate, 50*52*CCBHourlyRate ), IF(I52/H52<50, I52*52*(CCBHourlyRate-(G52-CCBThreshold)*CCBThresholdModifier), 50*52*(CCBHourlyRate-(G52-CCBThreshold)*CCBThresholdModifier) ) )) -> 0 | L52: =MIN((J52-K52) * CCRRate, (CCRMax*H52)) -> 6757.5 | M52: =J52-(K52+L52) -> 6757.5
A53: rodway-03 | B53: Rodway | C53: Austin | D53: Rodway | G53: 55513 | H53: =COUNTIF(Children!$B$13:$B$128,A53) -> 1 | I53: =10*SUMIFS(Children!$K$13:$K$128,Children!$B$13:$B$128,Families!A53) -> 40 | J53: =SUMIFS(Children!$Q$13:$Q$128,Children!$B$13:$B$128,Families!A53) -> 19305 | K53: =MAX(0,IF(G53<CCBThreshold, IF(I53/H53<CCBMaxHours, I53*52*CCBHourlyRate, 50*52*CCBHourlyRate ), IF(I53/H53<50, I53*52*(CCBHourlyRate-(G53-CCBThreshold)*CCBThresholdModifier), 50*52*(CCBHourlyRate-(G53-CCBThreshold)*CCBThresholdModifier) ) )) -> 1354.9255 | L53: =MIN((J53-K53) * CCRRate, (CCRMax*H53)) -> 7613 | M53: =J53-(K53+L53) -> 10337.074
A54: rule-02 | B54: Rule | C54: David | D54: Rule | E54: Alaina | F54: Rule | G54: 116031 | H54: =COUNTIF(Children!$B$13:$B$128,A54) -> 3 | I54: =10*SUMIFS(Children!$K$13:$K$128,Children!$B$13:$B$128,Families!A54) -> 90 | J54: =SUMIFS(Children!$Q$13:$Q$128,Children!$B$13:$B$128,Families!A54) -> 38430 | K54: =MAX(0,IF(G54<CCBThreshold, IF(I54/H54<CCBMaxHours, I54*52*CCBHourlyRate, 50*52*CCBHourlyRate ), IF(I54/H54<50, I54*52*(CCBHourlyRate-(G54-CCBThreshold)*CCBThresholdModifier), 50*52*(CCBHourlyRate-(G54-CCBThreshold)*CCBThresholdModifier) ) )) -> 1207.6249 | L54: =MIN((J54-K54) * CCRRate, (CCRMax*H54)) -> 18611.188 | M54: =J54-(K54+L54) -> 18611.188
A55: scherer-03 | B55: Scherer | C55: Niklas | D55: Scherer | E55: Leah | F55: Scherer | G55: 140101 | H55: =COUNTIF(Children!$B$13:$B$128,A55) -> 1 | I55: =10*SUMIFS(Children!$K$13:$K$128,Children!$B$13:$B$128,Families!A55) -> 20 | J55: =SUMIFS(Children!$Q$13:$Q$128,Children!$B$13:$B$128,Families!A55) -> 9570 | K55: =MAX(0,IF(G55<CCBThreshold, IF(I55/H55<CCBMaxHours, I55*52*CCBHourlyRate, 50*52*CCBHourlyRate ), IF(I55/H55<50, I55*52*(CCBHourlyRate-(G55-CCBThreshold)*CCBThresholdModifier), 50*52*(CCBHourlyRate-(G55-CCBThreshold)*CCBThresholdModifier) ) )) -> 105.64788 | L55: =MIN((J55-K55) * CCRRate, (CCRMax*H55)) -> 4732.1761 | M55: =J55-(K55+L55) -> 4732.1761
A56: seitz-01 | B56: Seitz | C56: Patrick | D56: Seitz | E56: Frank | F56: Gordon | G56: 208152 | H56: =COUNTIF(Children!$B$13:$B$128,A56) -> 1 | I56: =10*SUMIFS(Children!$K$13:$K$128,Children!$B$13:$B$128,Families!A56) -> 20 | J56: =SUMIFS(Children!$Q$13:$Q$128,Children!$B$13:$B$128,Families!A56) -> 9900 | K56: =MAX(0,IF(G56<CCBThreshold, IF(I56/H56<CCBMaxHours, I56*52*CCBHourlyRate, 50*52*CCBHourlyRate ), IF(I56/H56<50, I56*52*(CCBHourlyRate-(G56-CCBThreshold)*CCBThresholdModifier), 50*52*(CCBHourlyRate-(G56-CCBThreshold)*CCBThresholdModifier) ) )) -> 0 | L56: =MIN((J56-K56) * CCRRate, (CCRMax*H56)) -> 4950 | M56: =J56-(K56+L56) -> 4950
A57: shinosaki-02 | B57: Shinosaki | C57: Shuuji | D57: Shinosaki | E57: Kiyone | F57: Shinosaki | G57: 106277 | H57: =COUNTIF(Children!$B$13:$B$128,A57) -> 2 | I57: =10*SUMIFS(Children!$K$13:$K$128,Children!$B$13:$B$128,Families!A57) -> 80 | J57: =SUMIFS(Children!$Q$13:$Q$128,Children!$B$13:$B$128,Families!A57) -> 45905 | K57: =MAX(0,IF(G57<CCBThreshold, IF(I57/H57<CCBMaxHours, I57*52*CCBHourlyRate, 50*52*CCBHourlyRate ), IF(I57/H57<50, I57*52*(CCBHourlyRate-(G57-CCBThreshold)*CCBThresholdModifier), 50*52*(CCBHourlyRate-(G57-CCBThreshold)*CCBThresholdModifier) ) )) -> 1337.1925 | L57: =MIN((J57-K57) * CCRRate, (CCRMax*H57)) -> 15226 | M57: =J57-(K57+L57) -> 29341.808
A58: stirling-01 | B58: Stirling | C58: Dennis | D58: Stirling | E58: Monika | F58: Stirling | G58: 178119 | H58: =COUNTIF(Children!$B$13:$B$128,A58) -> 1 | I58: =10*SUMIFS(Children!$K$13:$K$128,Children!$B$13:$B$128,Families!A58) -> 30 | J58: =SUMIFS(Children!$Q$13:$Q$128,Children!$B$13:$B$128,Families!A58) -> 12065 | K58: =MAX(0,IF(G58<CCBThreshold, IF(I58/H58<CCBMaxHours, I58*52*CCBHourlyRate, 50*52*CCBHourlyRate ), IF(I58/H58<50, I58*52*(CCBHourlyRate-(G58-CCBThreshold)*CCBThresholdModifier), 50*52*(CCBHourlyRate-(G58-CCBThreshold)*CCBThresholdModifier) ) )) -> 0 | L58: =MIN((J58-K58) * CCRRate, (CCRMax*H58)) -> 6032.5 | M58: =J58-(K58+L58) -> 6032.5
A59: stopford-02 | B59: Stopford | C59: Brodie | D59: Stopford | E59: Natasha | F59: Stopford | G59: 190133 | H59: =COUNTIF(Children!$B$13:$B$128,A59) -> 1 | I59: =10*SUMIFS(Children!$K$13:$K$128,Children!$B$13:$B$128,Families!A59) -> 40 | J59: =SUMIFS(Children!$Q$13:$Q$128,Children!$B$13:$B$128,Families!A59) -> 14720 | K59: =MAX(0,IF(G59<CCBThreshold, IF(I59/H59<CCBMaxHours, I59*52*CCBHourlyRate, 50*52*CCBHourlyRate ), IF(I59/H59<50, I59*52*(CCBHourlyRate-(G59-CCBThreshold)*CCBThresholdModifier), 50*52*(CCBHourlyRate-(G59-CCBThreshold)*CCBThresholdModifier) ) )) -> 0 | L59: =MIN((J59-K59) * CCRRate, (CCRMax*H59)) -> 7360 | M59: =J59-(K59+L59) -> 7360
A60: sylvestre-01 | B60: Sylvestre | C60: Moses | D60: Sylvestre | E60: Mary | F60: Meekin | G60: 100968 | H60: =COUNTIF(Children!$B$13:$B$128,A60) -> 2 | I60: =10*SUMIFS(Children!$K$13:$K$128,Children!$B$13:$B$128,Families!A60) -> 120 | J60: =SUMIFS(Children!$Q$13:$Q$128,Children!$B$13:$B$128,Families!A60) -> 60865 | K60: =MAX(0,IF(G60<CCBThreshold, IF(I60/H60<CCBMaxHours, I60*52*CCBHourlyRate, 50*52*CCBHourlyRate ), IF(I60/H60<50, I60*52*(CCBHourlyRate-(G60-CCBThreshold)*CCBThresholdModifier), 50*52*(CCBHourlyRate-(G60-CCBThreshold)*CCBThresholdModifier) ) )) -> 925.4674 | L60: =MIN((J60-K60) * CCRRate, (CCRMax*H60)) -> 15226 | M60: =J60-(K60+L60) -> 44713.533
A61: tabata-02 | B61: Tabata | C61: Michie | D61: Tabata | E61: Yukihiro | F61: Tabata | G61: 156256 | H61: =COUNTIF(Children!$B$13:$B$128,A61) -> 2 | I61: =10*SUMIFS(Children!$K$13:$K$128,Children!$B$13:$B$128,Families!A61) -> 100 | J61: =SUMIFS(Children!$Q$13:$Q$128,Children!$B$13:$B$128,Families!A61) -> 50800 | K61: =MAX(0,IF(G61<CCBThreshold, IF(I61/H61<CCBMaxHours, I61*52*CCBHourlyRate, 50*52*CCBHourlyRate ), IF(I61/H61<50, I61*52*(CCBHourlyRate-(G61-CCBThreshold)*CCBThresholdModifier), 50*52*(CCBHourlyRate-(G61-CCBThreshold)*CCBThresholdModifier) ) )) -> 0 | L61: =MIN((J61-K61) * CCRRate, (CCRMax*H61)) -> 15226 | M61: =J61-(K61+L61) -> 35574
A62: takayama-01 | B62: Takayama | C62: Yukio | D62: Takayama | E62: Yumia | F62: Takayama | G62: 173190 | H62: =COUNTIF(Children!$B$13:$B$128,A62) -> 3 | I62: =10*SUMIFS(Children!$K$13:$K$128,Children!$B$13:$B$128,Families!A62) -> 180 | J62: =SUMIFS(Children!$Q$13:$Q$128,Children!$B$13:$B$128,Families!A62) -> 99260 | K62: =MAX(0,IF(G62<CCBThreshold, IF(I62/H62<CCBMaxHours, I62*52*CCBHourlyRate, 50*52*CCBHourlyRate ), IF(I62/H62<50, I62*52*(CCBHourlyRate-(G62-CCBThreshold)*CCBThresholdModifier), 50*52*(CCBHourlyRate-(G62-CCBThreshold)*CCBThresholdModifier) ) )) -> 0 | L62: =MIN((J62-K62) * CCRRate, (CCRMax*H62)) -> 22839 | M62: =J62-(K62+L62) -> 76421
A63: tani-01 | B63: Tani | C63: Itsumi | D63: Tani | E63: Hyouma | F63: Kawamura | G63: 100201 | H63: =COUNTIF(Children!$B$13:$B$128,A63) -> 2 | I63: =10*SUMIFS(Children!$K$13:$K$128,Children!$B$13:$B$128,Families!A63) -> 80 | J63: =SUMIFS(Children!$Q$13:$Q$128,Children!$B$13:$B$128,Families!A63) -> 36310 | K63: =MAX(0,IF(G63<CCBThreshold, IF(I63/H63<CCBMaxHours, I63*52*CCBHourlyRate, 50*52*CCBHourlyRate ), IF(I63/H63<50, I63*52*(CCBHourlyRate-(G63-CCBThreshold)*CCBThresholdModifier), 50*52*(CCBHourlyRate-(G63-CCBThreshold)*CCBThresholdModifier) ) )) -> 1501.4875 | L63: =MIN((J63-K63) * CCRRate, (CCRMax*H63)) -> 15226 | M63: =J63-(K63+L63) -> 19582.512
A64: tiller-02 | B64: Tiller | C64: Simone | D64: Tiller | E64: Marina | F64: Tiller | G64: 93612 | H64: =COUNTIF(Children!$B$13:$B$128,A64) -> 1 | I64: =10*SUMIFS(Children!$K$13:$K$128,Children!$B$13:$B$128,Families!A64) -> 30 | J64: =SUMIFS(Children!$Q$13:$Q$128,Children!$B$13:$B$128,Families!A64) -> 16170 | K64: =MAX(0,IF(G64<CCBThreshold, IF(I64/H64<CCBMaxHours, I64*52*CCBHourlyRate, 50*52*CCBHourlyRate ), IF(I64/H64<50, I64*52*(CCBHourlyRate-(G64-CCBThreshold)*CCBThresholdModifier), 50*52*(CCBHourlyRate-(G64-CCBThreshold)*CCBThresholdModifier) ) )) -> 629.87028 | L64: =MIN((J64-K64) * CCRRate, (CCRMax*H64)) -> 7613 | M64: =J64-(K64+L64) -> 7927.1297
A65: timbery-01 | B65: Timbery | C65: Eden | D65: Timbery | E65: Ethan | F65: Bentley | G65: 89272 | H65: =COUNTIF(Children!$B$13:$B$128,A65) -> 1 | I65: =10*SUMIFS(Children!$K$13:$K$128,Children!$B$13:$B$128,Families!A65) -> 30 | J65: =SUMIFS(Children!$Q$13:$Q$128,Children!$B$13:$B$128,Families!A65) -> 13860 | K65: =MAX(0,IF(G65<CCBThreshold, IF(I65/H65<CCBMaxHours, I65*52*CCBHourlyRate, 50*52*CCBHourlyRate ), IF(I65/H65<50, I65*52*(CCBHourlyRate-(G65-CCBThreshold)*CCBThresholdModifier), 50*52*(CCBHourlyRate-(G65-CCBThreshold)*CCBThresholdModifier) ) )) -> 673.87788 | L65: =MIN((J65-K65) * CCRRate, (CCRMax*H65)) -> 6593.0611 | M65: =J65-(K65+L65) -> 6593.0611
... A67: watson-01 | B67: Watson | C67: Kyle | D67: Watson | E67: Monique | F67: Creech | G67: 96445 | H67: =COUNTIF(Children!$B$13:$B$128,A67) -> 1 | I67: =10*SUMIFS(Children!$K$13:$K$128,Children!$B$13:$B$128,Families!A67) -> 10 | J67: =SUMIFS(Children!$Q$13:$Q$128,Children!$B$13:$B$128,Families!A67) -> 4740 | K67: =MAX(0,IF(G67<CCBThreshold, IF(I67/H67<CCBMaxHours, I67*52*CCBHourlyRate, 50*52*CCBHourlyRate ), IF(I67/H67<50, I67*52*(CCBHourlyRate-(G67-CCBThreshold)*CCBThresholdModifier), 50*52*(CCBHourlyRate-(G67-CCBThreshold)*CCBThresholdModifier) ) )) -> 200.38122 | L67: =MIN((J67-K67) * CCRRate, (CCRMax*H67)) -> 2269.8094 | M67: =J67-(K67+L67) -> 2269.8094
A68: winterbotham-03 | B68: Winterbotham | C68: Natasha | D68: Winterbotham | G68: 49824 | H68: =COUNTIF(Children!$B$13:$B$128,A68) -> 1 | I68: =10*SUMIFS(Children!$K$13:$K$128,Children!$B$13:$B$128,Families!A68) -> 30 | J68: =SUMIFS(Children!$Q$13:$Q$128,Children!$B$13:$B$128,Families!A68) -> 15015 | K68: =MAX(0,IF(G68<CCBThreshold, IF(I68/H68<CCBMaxHours, I68*52*CCBHourlyRate, 50*52*CCBHourlyRate ), IF(I68/H68<50, I68*52*(CCBHourlyRate-(G68-CCBThreshold)*CCBThresholdModifier), 50*52*(CCBHourlyRate-(G68-CCBThreshold)*CCBThresholdModifier) ) )) -> 1073.8806 | L68: =MIN((J68-K68) * CCRRate, (CCRMax*H68)) -> 6970.5597 | M68: =J68-(K68+L68) -> 6970.5597
A69: yoshihara-03 | B69: Yoshihara | C69: Tomoka | D69: Yoshihara | E69: Fukashi | F69: Cheng | G69: 188205 | H69: =COUNTIF(Children!$B$13:$B$128,A69) -> 2 | I69: =10*SUMIFS(Children!$K$13:$K$128,Children!$B$13:$B$128,Families!A69) -> 60 | J69: =SUMIFS(Children!$Q$13:$Q$128,Children!$B$13:$B$128,Families!A69) -> 31590 | K69: =MAX(0,IF(G69<CCBThreshold, IF(I69/H69<CCBMaxHours, I69*52*CCBHourlyRate, 50*52*CCBHourlyRate ), IF(I69/H69<50, I69*52*(CCBHourlyRate-(G69-CCBThreshold)*CCBThresholdModifier), 50*52*(CCBHourlyRate-(G69-CCBThreshold)*CCBThresholdModifier) ) )) -> 0 | L69: =MIN((J69-K69) * CCRRate, (CCRMax*H69)) -> 15226 | M69: =J69-(K69+L69) -> 16364
A70: yost-02 | B70: Yost | C70: Ruby | D70: Yost | E70: Salvador | F70: Nilsson | G70: 113211 | H70: =COUNTIF(Children!$B$13:$B$128,A70) -> 4 | I70: =10*SUMIFS(Children!$K$13:$K$128,Children!$B$13:$B$128,Families!A70) -> 200 | J70: =SUMIFS(Children!$Q$13:$Q$128,Children!$B$13:$B$128,Families!A70) -> 94430 | K70: =MAX(0,IF(G70<CCBThreshold, IF(I70/H70<CCBMaxHours, I70*52*CCBHourlyRate, 50*52*CCBHourlyRate ), IF(I70/H70<50, I70*52*(CCBHourlyRate-(G70-CCBThreshold)*CCBThresholdModifier), 50*52*(CCBHourlyRate-(G70-CCBThreshold)*CCBThresholdModifier) ) )) -> 718.5607 | L70: =MIN((J70-K70) * CCRRate, (CCRMax*H70)) -> 30452 | M70: =J70-(K70+L70) -> 63259.439

Sheet 2019 Planner
A2: Number of Children By Age | D2: Change | E2: Number of Children after change | H2: Average Number of Weekdays Per Week | I2: Attends Saturday | K2: Income
A3: 0 | B3: =COUNTIF(Children!$H$13:$H$128,A3) -> 13 | D3: 1 | E3: =B3*$D$3 -> 13 | H3: 3.5 | I3: 0.6 | K3: =(((VLOOKUP(A3,CareCosts,2,FALSE)) * E3 *$H$3) +( (VLOOKUP(A3,CareCosts,2,FALSE) + SaturdayPenalty) * E3 * $I$3) ) * (52) -> 336648
A4: 1 | B4: =COUNTIF(Children!$H$13:$H$128,A4) -> 12 | E4: =B4*$D$3 -> 12 | K4: =(((VLOOKUP(A4,CareCosts,2,FALSE)) * E4 *$H$3) +( (VLOOKUP(A4,CareCosts,2,FALSE) + SaturdayPenalty) * E4 * $I$3) ) * (52) -> 285168
A5: 2 | B5: =COUNTIF(Children!$H$13:$H$128,A5) -> 31 | E5: =B5*$D$3 -> 31 | K5: =(((VLOOKUP(A5,CareCosts,2,FALSE)) * E5 *$H$3) +( (VLOOKUP(A5,CareCosts,2,FALSE) + SaturdayPenalty) * E5 * $I$3) ) * (52) -> 703638
A6: 3 | B6: =COUNTIF(Children!$H$13:$H$128,A6) -> 32 | E6: =B6*$D$3 -> 32 | K6: =(((VLOOKUP(A6,CareCosts,2,FALSE)) * E6 *$H$3) +( (VLOOKUP(A6,CareCosts,2,FALSE) + SaturdayPenalty) * E6 * $I$3) ) * (52) -> 624000
A7: 4 | B7: =COUNTIF(Children!$H$13:$H$128,A7) -> 25 | E7: =B7*$D$3 -> 25 | K7: =(((VLOOKUP(A7,CareCosts,2,FALSE)) * E7 *$H$3) +( (VLOOKUP(A7,CareCosts,2,FALSE) + SaturdayPenalty) * E7 * $I$3) ) * (52) -> 460850
A8: 5 | B8: =COUNTIF(Children!$H$13:$H$128,A8) -> 3 | E8: =B8*$D$3 -> 3 | K8: =(((VLOOKUP(A8,CareCosts,2,FALSE)) * E8 *$H$3) +( (VLOOKUP(A8,CareCosts,2,FALSE) + SaturdayPenalty) * E8 * $I$3) ) * (52) -> 52104
J10: Total | K10: =SUM(K3:K8) -> 2462408
B17: Scenarios | C17: Current | D17: Low | E17: Mild Increase | F17: Medium Increase | G17: Major Increase
B18: Change | C18: 1 | D18: 0.8 | E18: 1.1 | F18: 1.2 | G18: 1.4
B19: Average Days | C19: 3.5 | D19: 2.5 | E19: 3.5 | F19: 4 | G19: 4.5
B20: Saturday | C20: 0.6 | D20: 0.4 | E20: 0.6 | F20: 0.6 | G20: 0.7

Sheet 2019 Scenario Summary
B2: 2019 Scenario Summary
D3: Current | E3: Low | F3: Mild Increase | G3: Medium Increase | H3: Major Increase
D4: Created by John on 5/19/2018 | E4: Created by John on 5/19/2018 | F4: Created by John on 5/19/2018 | G4: Created by John on 5/19/2018 | H4: Created by John on 5/19/2018
B5: Changing Cells:
C6: Change Rate in Number of Student | D6: 1 | E6: 0.8 | F6: 1.1 | G6: 1.2 | H6: 1.4
C7: Average Weekday Attendence | D7: 3.5 | E7: 2.5 | F7: 3.5 | G7: 4 | H7: 4.5
C8: Average Saturday Attendence | D8: 0.6 | E8: 0.4 | F8: 0.6 | G8: 0.6 | H8: 0.7
B9: Result Cells:
C10: Number of 0 year old children | D10: 13 | E10: 10.4 | F10: 14.3 | G10: 15.6 | H10: 18.2
C11: Number of 1 year old children | D11: 12 | E11: 9.6 | F11: 13.2 | G11: 14.4 | H11: 16.8
C12: Number of 2 years old children | D12: 31 | E12: 24.8 | F12: 34.1 | G12: 37.2 | H12: 43.4
C13: Number of 3 years old children | D13: 32 | E13: 25.6 | F13: 35.2 | G13: 38.4 | H13: 44.8
C14: Number of 4 years old children | D14: 25 | E14: 20 | F14: 27.5 | G14: 30 | H14: 35
C15: Number of 5 years old children | D15: 3 | E15: 2.4 | F15: 3.3 | G15: 3.6 | H15: 4.2
C16: Income from 0 year old children | D16: 336648 | E16: 190361.6 | F16: 370312.8 | G16: 452649.6 | H16: 597178.4
C17: Income from 1 year old children | D17: 285168 | E17: 161241.6 | F17: 313684.8 | G17: 383385.6 | H17: 505814.4
C18: Income from 2 years old children | D18: 703638 | E18: 397841.6 | F18: 774001.8 | G18: 945921.6 | H18: 1248010.4
C19: Income from 3 years old children | D19: 624000 | E19: 352768 | F19: 686400 | G19: 838656 | H19: 1106560
C20: Income from 4 years old children | D20: 460850 | E20: 260520 | F20: 506935 | G20: 619320 | H20: 817180
C21: Income from 5 years old children | D21: 52104 | E21: 29452.8 | F21: 57314.4 | G21: 70012.8 | H21: 92383.2
C22: Total Annual Income | D22: 2462408 | E22: 1392185.6 | F22: 2708648.8 | G22: 3309945.6 | H22: 4367126.4

Sheet Investment Answer Report
A1: Microsoft Excel 16.0 Answer Report
A2: Worksheet: [ggwp.xlsx]Investment Planning
A3: Report Created: 5/19/2018 4:12:47 PM
A4: Result: Solver has converged to the current solution. All Constraints are satisfied.
A5: Solver Engine
B6: Engine: GRG Nonlinear
B7: Solution Time: 0.234 Seconds.
B8: Iterations: 10 Subproblems: 0
A9: Solver Options
B10: Max Time Unlimited, Iterations Unlimited, Precision 0.000001, Use Automatic Scaling
B11: Convergence 0.0001, Population Size 100, Random Seed 0, Derivatives Forward, Require Bounds
B12: Max Subproblems Unlimited, Max Integer Sols Unlimited, Integer Tolerance 1%, Assume NonNegative
A14: Objective Cell (Max)
B15: Cell | C15: Name | D15: Original Value | E15: Final Value
B16: $C$13 | C16: Total Return Return | D16: 0 | E16: 8883.0752
A19: Variable Cells
B20: Cell | C20: Name | D20: Original Value | E20: Final Value | F20: Integer
B21: $B$3 | C21: Central Brisbane Finance Investment | D21: 0 | E21: 23384.964 | F21: Contin
B22: $B$4 | C22: North Brisbane Finance Investment | D22: 0 | E22: 26615.036 | F22: Contin
B23: $B$5 | C23: East Brisbane Finance Investment | D23: 0 | E23: 26615.036 | F23: Contin
B24: $B$6 | C24: South Brisbane Finance Investment | D24: 0 | E24: 0 | F24: Contin
B25: $B$7 | C25: West Brisbane Finance Investment | D25: 0 | E25: 23384.964 | F25: Contin
A28: Constraints
B29: Cell | C29: Name | D29: Cell Value | E29: Formula | F29: Status | G29: Slack
B30: $B$9 | C30: Total Investments Investment | D30: 100000 | E30: $B$9<=$B$11 | F30: Binding | G30: 0
B31: $E$9 | C31: Total Short Term | D31: 50000 | E31: $E$9>=0.5 * $B$11 | F31: Binding | G31: 0
B32: $G$9 | C32: Total High Risk | D32: 50000 | E32: $G$9<=0.5 * $B$11 | F32: Binding | G32: 0
B33: $I$13 | C33: Tax-Free Return | D33: 4092.3687 | E33: $I$13>=0.3 * $C$13 | F33: Not Binding | G33: 1427.4462
B34: $I$9 | C34: Total Tax Free | D34: 46769.928 | E34: $I$9>=0.3 * $B$11 | F34: Not Binding | G34: 16769.928

Sheet Investment Planning
A1: Sunshine Investment Planning
A2: Account | B2: Investment | C2: Return | D2: Matuarity | F2: Risk Rating | H2: Tax-Free
A3: Central Brisbane Finance | B3: 0 | C3: 0.08 | D3: Short | E3: 1 | F3: Low | G3: 0 | H3: Yes | I3: 1
A4: North Brisbane Finance | B4: 0 | C4: 0.09 | D4: Short | E4: 1 | F4: High | G4: 1 | H4: No | I4: 0
A5: East Brisbane Finance | B5: 0 | C5: 0.09 | D5: Long | E5: 0 | F5: Low | G5: 0 | H5: No | I5: 0
A6: South Brisbane Finance | B6: 0 | C6: 0.09 | D6: Long | E6: 0 | F6: High | G6: 1 | H6: Yes | I6: 1
A7: West Brisbane Finance | B7: 0 | C7: 0.095 | D7: Long | E7: 0 | F7: High | G7: 1 | H7: Yes | I7: 1
A9: Total Investments | B9: =SUM(B3:B7) -> 0 | D9: Total Short Term | E9: =SUMPRODUCT(E3:E7,$B$3:$B$7) -> 0 | F9: Total High Risk | G9: =SUMPRODUCT(G3:G7,$B$3:$B$7) -> 0 | H9: Total Tax Free | I9: =SUMPRODUCT(I3:I7,$B$3:$B$7) -> 0
A11: Available Funds | B11: 100000
B13: Total Return | C13: =SUMPRODUCT(C3:C7,$B$3:$B$7) -> 0 | H13: Tax-Free Return | I13: =SUMPRODUCT($B$3:B7,C3:C7,I3:I7) -> 0
